{"assets":{"A39890CA799CAA1EBF0B9EE97BE370DD":{"type":"texture","index":7,"assetRequest":{"type":"slide","state":"contents","slide":"3B30B27C-5654-4523-9418-7612538828F6"},"url":{"web":"assets/3B30B27C-5654-4523-9418-7612538828F6.svgmap"},"width":96,"height":52},"1FBF80488DA9D9CD43214480320209F2":{"type":"texture","index":2,"assetRequest":{"type":"slide","state":"contents","slide":"3B30B27C-5654-4523-9418-7612538828F6"},"url":{"web":"assets/3B30B27C-5654-4523-9418-7612538828F6.svgmap"},"width":1922,"height":109},"BDB8E63E646B8A3223E470DDFAFD49BB":{"type":"texture","index":1,"assetRequest":{"type":"slide","state":"contents","slide":"3B30B27C-5654-4523-9418-7612538828F6"},"url":{"web":"assets/3B30B27C-5654-4523-9418-7612538828F6.svgmap"},"width":1920,"height":1187},"FB324C4DDB5BB68F728CB212B42EF667":{"type":"texture","index":5,"assetRequest":{"type":"slide","state":"contents","slide":"3B30B27C-5654-4523-9418-7612538828F6"},"url":{"web":"assets/3B30B27C-5654-4523-9418-7612538828F6.svgmap"},"width":543,"height":241},"F1E4F471EFBCA02A7A50F8183033FDEE":{"type":"texture","index":11,"assetRequest":{"type":"slide","state":"contents","slide":"3B30B27C-5654-4523-9418-7612538828F6"},"url":{"web":"assets/3B30B27C-5654-4523-9418-7612538828F6.svgmap"},"width":153,"height":65},"3A6AA7E13049CA43A0D406F83530A09D":{"type":"texture","index":12,"assetRequest":{"type":"slide","state":"contents","slide":"3B30B27C-5654-4523-9418-7612538828F6"},"url":{"web":"assets/3B30B27C-5654-4523-9418-7612538828F6.svgmap"},"width":169,"height":80},"32421F0B3E0C6634C0C341CD41DF516D":{"type":"texture","index":14,"assetRequest":{"type":"slide","state":"incoming","slide":"DC16F59C-1CD5-41A3-AF09-F2D13B1D95D0"},"url":{"web":"assets/3B30B27C-5654-4523-9418-7612538828F6.svgmap"},"width":1920,"height":1080},"0DB6C110A922BC749D0CD1B6CECD6B2C":{"type":"texture","index":8,"assetRequest":{"type":"slide","state":"contents","slide":"3B30B27C-5654-4523-9418-7612538828F6"},"url":{"web":"assets/3B30B27C-5654-4523-9418-7612538828F6.svgmap"},"width":96,"height":53},"F103F82652D757B9580E25359DE65B05":{"type":"texture","index":6,"assetRequest":{"type":"slide","state":"contents","slide":"3B30B27C-5654-4523-9418-7612538828F6"},"url":{"web":"assets/3B30B27C-5654-4523-9418-7612538828F6.svgmap"},"width":97,"height":52},"C25C25FF361FB24FC35F6B120D2F252D":{"type":"texture","index":0,"assetRequest":{"type":"slide","state":"contents","slide":"3B30B27C-5654-4523-9418-7612538828F6"},"url":{"web":"assets/3B30B27C-5654-4523-9418-7612538828F6.svgmap"},"width":1920,"height":1080},"2D6FAE11570D11BD139BBDFCBD5B0B84":{"type":"texture","index":3,"assetRequest":{"type":"slide","state":"contents","slide":"3B30B27C-5654-4523-9418-7612538828F6"},"url":{"web":"assets/3B30B27C-5654-4523-9418-7612538828F6.svgmap"},"width":670,"height":252},"FB604898F4125EE5D77E90AA5878BA5A":{"type":"texture","index":13,"assetRequest":{"type":"slide","state":"outgoing","slide":"3B30B27C-5654-4523-9418-7612538828F6"},"url":{"web":"assets/3B30B27C-5654-4523-9418-7612538828F6.svgmap"},"width":1920,"height":1080},"0A76BA58503224FEEDCA4872F8618A58":{"type":"texture","index":10,"assetRequest":{"type":"slide","state":"contents","slide":"3B30B27C-5654-4523-9418-7612538828F6"},"url":{"web":"assets/3B30B27C-5654-4523-9418-7612538828F6.svgmap"},"width":154,"height":81},"28AB14DD929655C84A34F48A511892A5":{"type":"texture","index":4,"assetRequest":{"type":"slide","state":"contents","slide":"3B30B27C-5654-4523-9418-7612538828F6"},"url":{"web":"assets/3B30B27C-5654-4523-9418-7612538828F6.svgmap"},"width":543,"height":444},"0AFD695DF00B56CFBA35BE358E1C9D6B":{"type":"texture","index":9,"assetRequest":{"type":"slide","state":"contents","slide":"3B30B27C-5654-4523-9418-7612538828F6"},"url":{"web":"assets/3B30B27C-5654-4523-9418-7612538828F6.svgmap"},"width":109,"height":109}},"events":[{"effects":[{"beginTime":0,"baseLayer":{"animations":[],"initialState":{"affineTransform":[1,0,0,1,0,0],"masksToBounds":false,"rotation":0,"scale":1,"position":{"pointX":960,"pointY":289.0942358970642},"width":666.454345703125,"sublayerTransform":[1,0,0,0,0,1,0,0,0,0,1,0,0,0,0,1],"contentsRect":{"y":0,"x":0,"width":1,"height":1},"opacity":1,"edgeAntialiasingMask":251658240,"height":249.2924757003784,"hidden":false,"anchorPoint":{"pointX":0.5,"pointY":0.5}},"objectID":"E43A25C0-998F-45E8-BFA1-BCC657B0FCBF","layers":[{"animations":[],"initialState":{"affineTransform":[1,0,0,1,0,0],"masksToBounds":false,"rotation":0,"scale":1,"position":{"pointX":333.2271728515625,"pointY":375.552001953125},"width":666.454345703125,"sublayerTransform":[1,0,0,0,0,1,0,0,0,0,1,-0.0003500791246677598,0,0,0,1],"contentsRect":{"y":0,"x":0,"width":1,"height":1},"opacity":1,"edgeAntialiasingMask":251658240,"height":249.2924757003784,"hidden":false,"anchorPoint":{"pointX":0.5,"pointY":1.506471468495088}},"layers":[{"animations":[{"timeOffset":0,"beginTime":1e-100,"repeatCount":0,"animations":[{"timeOffset":0,"from":{"scalar":0},"beginTime":0,"repeatCount":0,"fillMode":"both","duration":1,"autoreverses":false,"timingFunction":"EaseInEaseOut","property":"opacity","to":{"scalar":1}},{"timeOffset":0,"from":{"scalar":false},"beginTime":0,"repeatCount":0,"fillMode":"forwards","property":"hidden","autoreverses":false,"duration":1,"to":{"scalar":false}}],"fillMode":"both","autoreverses":false,"duration":1}],"layers":[],"texturedRectangle":{"singleTextureOpacity":1,"textXHeight":0,"shapePath":{"lineWidth":1,"flatness":0.6,"lineCapStyle":0,"elements":[{"type":"MoveToPoint","points":[[568.1523198052309,40.43090961984672]]},{"type":"AddCurve","points":[[696.918790533673,87.741458383809],[696.918790533673,164.4470134103194],[568.1523198052309,211.7575621742817]]},{"type":"AddCurve","points":[[439.3858490767889,259.068110938244],[230.6141509232111,259.068110938244],[101.8476801947691,211.7575621742817]]},{"type":"AddCurve","points":[[-26.91879053367302,164.4470134103194],[-26.91879053367302,87.741458383809],[101.8476801947691,40.43090961984672]]},{"type":"AddCurve","points":[[230.6141509232111,-6.879639144115572],[439.3858490767889,-6.879639144115572],[568.1523198052309,40.43090961984672]]},{"type":"CloseSubpath"},{"type":"MoveToPoint","points":[[568.1523198052309,40.43090961984672]]}],"windingRule":0,"lineJoinStyle":0,"miterLimit":10},"isBackgroundTexture":true,"textBaseline":0,"isVerticalText":false,"textureType":5},"initialState":{"affineTransform":[1,0,0,1,0,0],"masksToBounds":false,"rotation":0,"scale":1,"position":{"pointX":333.2271728515625,"pointY":124.552001953125},"width":670,"sublayerTransform":[1,0,0,0,0,1,0,0,0,0,1,0,0,0,0,1],"contentsRect":{"y":0,"x":0,"width":1,"height":1},"opacity":1,"edgeAntialiasingMask":0,"height":252,"hidden":true,"anchorPoint":{"pointX":0.5,"pointY":0.5}},"texture":"2D6FAE11570D11BD139BBDFCBD5B0B84"}]}]},"effects":[{"beginTime":0,"baseLayer":{"animations":[],"initialState":{"affineTransform":[1,0,0,1,0,0],"masksToBounds":false,"rotation":0,"scale":1,"position":{"pointX":1388.788191229105,"pointY":841.1545858383179},"width":504.38790589571,"sublayerTransform":[1,0,0,0,0,1,0,0,0,0,1,0,0,0,0,1],"contentsRect":{"y":0,"x":0,"width":1,"height":1},"opacity":1,"edgeAntialiasingMask":251658240,"height":401.1777019500732,"hidden":false,"anchorPoint":{"pointX":0.5,"pointY":0.5}},"objectID":"0E6961F4-4873-41F8-8151-E74DAD01F4EF","layers":[{"animations":[],"initialState":{"affineTransform":[1,0,0,1,0,0],"masksToBounds":false,"rotation":0,"scale":1,"position":{"pointX":-176.59423828125,"pointY":-100.5657348632812},"width":504.38790589571,"sublayerTransform":[1,0,0,0,0,1,0,0,0,0,1,-0.0003500791246677598,0,0,0,1],"contentsRect":{"y":0,"x":0,"width":1,"height":1},"opacity":1,"edgeAntialiasingMask":251658240,"height":401.1777019500732,"hidden":false,"anchorPoint":{"pointX":-0.3501159250986553,"pointY":-0.2506762822919722}},"layers":[{"animations":[{"timeOffset":0,"beginTime":1e-100,"repeatCount":0,"animations":[{"timeOffset":0,"from":{"scalar":0},"beginTime":0,"repeatCount":0,"fillMode":"both","duration":1,"autoreverses":false,"timingFunction":"EaseInEaseOut","property":"opacity","to":{"scalar":1}},{"timeOffset":0,"from":{"scalar":false},"beginTime":0,"repeatCount":0,"fillMode":"forwards","property":"hidden","autoreverses":false,"duration":1,"to":{"scalar":false}}],"fillMode":"both","autoreverses":false,"duration":1}],"layers":[],"texturedRectangle":{"singleTextureOpacity":1,"textXHeight":0,"shapePath":{"lineWidth":1,"flatness":0.6,"lineCapStyle":0,"elements":[{"type":"MoveToPoint","points":[[19.59423828125,21.56573486328125]]},{"type":"AddLine","points":[[523.98214417696,21.56573486328125]]},{"type":"AddLine","points":[[523.98214417696,422.7434368133545]]},{"type":"AddLine","points":[[19.59423828125,422.7434368133545]]},{"type":"CloseSubpath"},{"type":"MoveToPoint","points":[[19.59423828125,21.56573486328125]]}],"windingRule":0,"lineJoinStyle":0,"miterLimit":10},"isBackgroundTexture":true,"textBaseline":0,"isVerticalText":false,"textureType":5},"initialState":{"affineTransform":[1,0,0,1,0,0],"masksToBounds":false,"rotation":0,"scale":1,"position":{"pointX":251.90576171875,"pointY":200.4342651367188},"width":543,"sublayerTransform":[1,0,0,0,0,1,0,0,0,0,1,0,0,0,0,1],"contentsRect":{"y":0,"x":0,"width":1,"height":1},"opacity":1,"edgeAntialiasingMask":0,"height":444,"hidden":true,"anchorPoint":{"pointX":0.5,"pointY":0.5}},"texture":"28AB14DD929655C84A34F48A511892A5"}]}]},"effects":[],"duration":1,"type":"buildIn","attributes":{"direction":0},"name":"com.apple.iWork.Keynote.FromDarkness","objectID":"0E6961F4-4873-41F8-8151-E74DAD01F4EF"}],"duration":1,"type":"buildIn","attributes":{"direction":0},"name":"com.apple.iWork.Keynote.FromDarkness","objectID":"E43A25C0-998F-45E8-BFA1-BCC657B0FCBF"}],"automaticPlay":true,"hyperlinks":[],"accessibility":[{"text":"droppedImage.pdf","targetRectangle":{"y":0,"x":0,"width":106.3778686523438,"height":106.3778686523438}},{"text":"logo_idb_black.png","targetRectangle":{"y":14.40425872802734,"x":1726.216796875,"width":166.3303070068359,"height":77.56935119628906}},{"text":"Logo Waze Branco.png","targetRectangle":{"y":998.6266479492188,"x":1748.386474609375,"width":149.7072296142578,"height":61.6969108581543}},{"text":"AV. BRASIL / PRESIDENTE DUTRA","targetRectangle":{"y":18.81250262260437,"x":533.1060375509261,"width":853.7880000000004,"height":62.49163818359375}},{"text":"logo_vertical.png","targetRectangle":{"y":990.3093872070312,"x":9.939437866210938,"width":150.0625,"height":78.66712951660156}},{"text":"01-Brasil-Dutra.png","targetRectangle":{"y":1.84375,"x":1,"width":1918,"height":1183.539306640625}}],"baseLayer":{"animations":[],"initialState":{"affineTransform":[1,0,0,1,0,0],"masksToBounds":false,"rotation":0,"scale":1,"position":{"pointX":960,"pointY":540},"width":1920,"sublayerTransform":[1,0,0,0,0,1,0,0,0,0,1,0,0,0,0,1],"contentsRect":{"y":0,"x":0,"width":1,"height":1},"opacity":1,"edgeAntialiasingMask":251658240,"height":1080,"hidden":false,"anchorPoint":{"pointX":0.5,"pointY":0.5}},"layers":[{"animations":[],"initialState":{"affineTransform":[1,0,0,1,0,0],"masksToBounds":false,"rotation":0,"scale":1,"position":{"pointX":960,"pointY":540},"width":1920,"sublayerTransform":[1,0,0,0,0,1,0,0,0,0,1,0,0,0,0,1],"contentsRect":{"y":0,"x":0,"width":1,"height":1},"opacity":1,"edgeAntialiasingMask":251658240,"height":1080,"hidden":false,"anchorPoint":{"pointX":0.5,"pointY":0.5}},"layers":[{"animations":[],"initialState":{"affineTransform":[1,0,0,1,0,0],"masksToBounds":false,"rotation":0,"scale":1,"position":{"pointX":960,"pointY":540},"width":1920,"sublayerTransform":[1,0,0,0,0,1,0,0,0,0,1,0,0,0,0,1],"contentsRect":{"y":0,"x":0,"width":1,"height":1},"opacity":1,"edgeAntialiasingMask":251658240,"height":1080,"hidden":false,"anchorPoint":{"pointX":0.5,"pointY":0.5}},"layers":[{"animations":[],"layers":[],"texturedRectangle":{"isBackgroundTexture":true,"singleTextureOpacity":1,"textureType":1,"textBaseline":0,"textXHeight":0,"isVerticalText":false},"initialState":{"affineTransform":[1,0,0,1,0,0],"masksToBounds":false,"rotation":0,"scale":1,"position":{"pointX":960,"pointY":540},"width":1920,"sublayerTransform":[1,0,0,0,0,1,0,0,0,0,1,0,0,0,0,1],"contentsRect":{"y":0,"x":0,"width":1,"height":1},"opacity":1,"edgeAntialiasingMask":0,"height":1080,"hidden":false,"anchorPoint":{"pointX":0.5,"pointY":0.5}},"texture":"C25C25FF361FB24FC35F6B120D2F252D"}]}]},{"animations":[],"initialState":{"affineTransform":[1,0,0,1,0,0],"masksToBounds":false,"rotation":0,"scale":1,"position":{"pointX":960,"pointY":540},"width":1920,"sublayerTransform":[1,0,0,0,0,1,0,0,0,0,1,0,0,0,0,1],"contentsRect":{"y":0,"x":0,"width":1,"height":1},"opacity":1,"edgeAntialiasingMask":251658240,"height":1080,"hidden":false,"anchorPoint":{"pointX":0.5,"pointY":0.5}},"layers":[{"animations":[],"initialState":{"affineTransform":[1,0,0,1,0,0],"masksToBounds":false,"rotation":0,"scale":1,"position":{"pointX":960,"pointY":593.6134033203125},"width":1918,"sublayerTransform":[1,0,0,0,0,1,0,0,0,0,1,0,0,0,0,1],"contentsRect":{"y":0,"x":0,"width":1,"height":1},"opacity":1,"edgeAntialiasingMask":251658240,"height":1183.539306640625,"hidden":false,"anchorPoint":{"pointX":0.5,"pointY":0.5}},"objectID":"78B5E340-7EF1-464F-88CE-D000F6A0C81E","layers":[{"animations":[],"layers":[],"texturedRectangle":{"isBackgroundTexture":true,"singleTextureOpacity":1,"textureType":5,"textBaseline":0,"textXHeight":0,"isVerticalText":false},"initialState":{"affineTransform":[1,0,0,1,0,0],"masksToBounds":false,"rotation":0,"scale":1,"position":{"pointX":959,"pointY":591.65625},"width":1920,"sublayerTransform":[1,0,0,0,0,1,0,0,0,0,1,0,0,0,0,1],"contentsRect":{"y":0,"x":0,"width":1,"height":1},"opacity":1,"edgeAntialiasingMask":0,"height":1187,"hidden":false,"anchorPoint":{"pointX":0.5,"pointY":0.5}},"texture":"BDB8E63E646B8A3223E470DDFAFD49BB"}]}]},{"animations":[],"initialState":{"affineTransform":[1,0,0,1,0,0],"masksToBounds":false,"rotation":0,"scale":1,"position":{"pointX":960,"pointY":540},"width":1920,"sublayerTransform":[1,0,0,0,0,1,0,0,0,0,1,0,0,0,0,1],"contentsRect":{"y":0,"x":0,"width":1,"height":1},"opacity":1,"edgeAntialiasingMask":251658240,"height":1080,"hidden":false,"anchorPoint":{"pointX":0.5,"pointY":0.5}},"layers":[{"animations":[],"initialState":{"affineTransform":[1,0,0,1,0,0],"masksToBounds":false,"rotation":0,"scale":1,"position":{"pointX":960.0000165700912,"pointY":50.37643754482269},"width":1919.218585968018,"sublayerTransform":[1,0,0,0,0,1,0,0,0,0,1,0,0,0,0,1],"contentsRect":{"y":0,"x":0,"width":1,"height":1},"opacity":1,"edgeAntialiasingMask":251658240,"height":106.3778698444366,"hidden":false,"anchorPoint":{"pointX":0.5,"pointY":0.5}},"objectID":"BF198EBE-308C-465F-90FB-70B7657CE152","layers":[{"animations":[],"layers":[],"texturedRectangle":{"singleTextureOpacity":1,"textXHeight":0,"shapePath":{"lineWidth":1,"flatness":0.6,"lineCapStyle":0,"elements":[{"type":"MoveToPoint","points":[[1.390723586082458,1.18750262260437]]},{"type":"AddLine","points":[[1920.6093095541,1.18750262260437]]},{"type":"AddLine","points":[[1920.6093095541,107.565372467041]]},{"type":"AddLine","points":[[1.390723586082458,107.565372467041]]},{"type":"CloseSubpath"},{"type":"MoveToPoint","points":[[1.390723586082458,1.18750262260437]]}],"windingRule":0,"lineJoinStyle":0,"miterLimit":10},"isBackgroundTexture":true,"textBaseline":0,"isVerticalText":false,"textureType":5},"initialState":{"affineTransform":[1,0,0,1,0,0],"masksToBounds":false,"rotation":0,"scale":1,"position":{"pointX":959.6092764139175,"pointY":53.31249737739563},"width":1922,"sublayerTransform":[1,0,0,0,0,1,0,0,0,0,1,0,0,0,0,1],"contentsRect":{"y":0,"x":0,"width":1,"height":1},"opacity":1,"edgeAntialiasingMask":0,"height":109,"hidden":false,"anchorPoint":{"pointX":0.5,"pointY":0.5}},"texture":"1FBF80488DA9D9CD43214480320209F2"}]}]},{"animations":[],"initialState":{"affineTransform":[1,0,0,1,0,0],"masksToBounds":false,"rotation":0,"scale":1,"position":{"pointX":960,"pointY":540},"width":1920,"sublayerTransform":[1,0,0,0,0,1,0,0,0,0,1,0,0,0,0,1],"contentsRect":{"y":0,"x":0,"width":1,"height":1},"opacity":1,"edgeAntialiasingMask":251658240,"height":1080,"hidden":false,"anchorPoint":{"pointX":0.5,"pointY":0.5}},"layers":[{"animations":[],"initialState":{"affineTransform":[1,0,0,1,0,0],"masksToBounds":false,"rotation":0,"scale":1,"position":{"pointX":960,"pointY":289.0942358970642},"width":666.454345703125,"sublayerTransform":[1,0,0,0,0,1,0,0,0,0,1,0,0,0,0,1],"contentsRect":{"y":0,"x":0,"width":1,"height":1},"opacity":1,"edgeAntialiasingMask":251658240,"height":249.2924757003784,"hidden":false,"anchorPoint":{"pointX":0.5,"pointY":0.5}},"objectID":"E43A25C0-998F-45E8-BFA1-BCC657B0FCBF","layers":[{"animations":[],"layers":[],"texturedRectangle":{"singleTextureOpacity":1,"textXHeight":0,"shapePath":{"lineWidth":1,"flatness":0.6,"lineCapStyle":0,"elements":[{"type":"MoveToPoint","points":[[568.1523198052309,40.43090961984672]]},{"type":"AddCurve","points":[[696.918790533673,87.741458383809],[696.918790533673,164.4470134103194],[568.1523198052309,211.7575621742817]]},{"type":"AddCurve","points":[[439.3858490767889,259.068110938244],[230.6141509232111,259.068110938244],[101.8476801947691,211.7575621742817]]},{"type":"AddCurve","points":[[-26.91879053367302,164.4470134103194],[-26.91879053367302,87.741458383809],[101.8476801947691,40.43090961984672]]},{"type":"AddCurve","points":[[230.6141509232111,-6.879639144115572],[439.3858490767889,-6.879639144115572],[568.1523198052309,40.43090961984672]]},{"type":"CloseSubpath"},{"type":"MoveToPoint","points":[[568.1523198052309,40.43090961984672]]}],"windingRule":0,"lineJoinStyle":0,"miterLimit":10},"isBackgroundTexture":true,"textBaseline":0,"isVerticalText":false,"textureType":5},"initialState":{"affineTransform":[1,0,0,1,0,0],"masksToBounds":false,"rotation":0,"scale":1,"position":{"pointX":333.2271728515625,"pointY":124.552001953125},"width":670,"sublayerTransform":[1,0,0,0,0,1,0,0,0,0,1,0,0,0,0,1],"contentsRect":{"y":0,"x":0,"width":1,"height":1},"opacity":1,"edgeAntialiasingMask":0,"height":252,"hidden":true,"anchorPoint":{"pointX":0.5,"pointY":0.5}},"texture":"2D6FAE11570D11BD139BBDFCBD5B0B84"}]}]},{"animations":[],"initialState":{"affineTransform":[1,0,0,1,0,0],"masksToBounds":false,"rotation":0,"scale":1,"position":{"pointX":960,"pointY":540},"width":1920,"sublayerTransform":[1,0,0,0,0,1,0,0,0,0,1,0,0,0,0,1],"contentsRect":{"y":0,"x":0,"width":1,"height":1},"opacity":1,"edgeAntialiasingMask":251658240,"height":1080,"hidden":false,"anchorPoint":{"pointX":0.5,"pointY":0.5}},"layers":[{"animations":[],"initialState":{"affineTransform":[1,0,0,1,0,0],"masksToBounds":false,"rotation":0,"scale":1,"position":{"pointX":1388.788191229105,"pointY":841.1545858383179},"width":504.38790589571,"sublayerTransform":[1,0,0,0,0,1,0,0,0,0,1,0,0,0,0,1],"contentsRect":{"y":0,"x":0,"width":1,"height":1},"opacity":1,"edgeAntialiasingMask":251658240,"height":401.1777019500732,"hidden":false,"anchorPoint":{"pointX":0.5,"pointY":0.5}},"objectID":"0E6961F4-4873-41F8-8151-E74DAD01F4EF","layers":[{"animations":[],"layers":[],"texturedRectangle":{"singleTextureOpacity":1,"textXHeight":0,"shapePath":{"lineWidth":1,"flatness":0.6,"lineCapStyle":0,"elements":[{"type":"MoveToPoint","points":[[19.59423828125,21.56573486328125]]},{"type":"AddLine","points":[[523.98214417696,21.56573486328125]]},{"type":"AddLine","points":[[523.98214417696,422.7434368133545]]},{"type":"AddLine","points":[[19.59423828125,422.7434368133545]]},{"type":"CloseSubpath"},{"type":"MoveToPoint","points":[[19.59423828125,21.56573486328125]]}],"windingRule":0,"lineJoinStyle":0,"miterLimit":10},"isBackgroundTexture":true,"textBaseline":0,"isVerticalText":false,"textureType":5},"initialState":{"affineTransform":[1,0,0,1,0,0],"masksToBounds":false,"rotation":0,"scale":1,"position":{"pointX":251.90576171875,"pointY":200.4342651367188},"width":543,"sublayerTransform":[1,0,0,0,0,1,0,0,0,0,1,0,0,0,0,1],"contentsRect":{"y":0,"x":0,"width":1,"height":1},"opacity":1,"edgeAntialiasingMask":0,"height":444,"hidden":true,"anchorPoint":{"pointX":0.5,"pointY":0.5}},"texture":"28AB14DD929655C84A34F48A511892A5"}]}]},{"animations":[],"initialState":{"affineTransform":[1,0,0,1,0,0],"masksToBounds":false,"rotation":0,"scale":1,"position":{"pointX":960,"pointY":540},"width":1920,"sublayerTransform":[1,0,0,0,0,1,0,0,0,0,1,0,0,0,0,1],"contentsRect":{"y":0,"x":0,"width":1,"height":1},"opacity":1,"edgeAntialiasingMask":251658240,"height":1080,"hidden":false,"anchorPoint":{"pointX":0.5,"pointY":0.5}},"layers":[{"animations":[],"initialState":{"affineTransform":[1,0,0,1,0,0],"masksToBounds":false,"rotation":0,"scale":1,"position":{"pointX":529.569441229105,"pointY":841.1545872688293},"width":504.38790589571,"sublayerTransform":[1,0,0,0,0,1,0,0,0,0,1,0,0,0,0,1],"contentsRect":{"y":0,"x":0,"width":1,"height":1},"opacity":1,"edgeAntialiasingMask":251658240,"height":198.1386423110962,"hidden":false,"anchorPoint":{"pointX":0.5,"pointY":0.5}},"objectID":"D6F34A34-5201-48E8-B6AB-52BCCE77C11C","layers":[{"animations":[],"layers":[],"texturedRectangle":{"singleTextureOpacity":1,"textXHeight":0,"shapePath":{"lineWidth":1,"flatness":0.6,"lineCapStyle":0,"elements":[{"type":"MoveToPoint","points":[[19.37548828125,21.08526611328125]]},{"type":"AddLine","points":[[523.76339417696,21.08526611328125]]},{"type":"AddLine","points":[[523.76339417696,219.2239084243774]]},{"type":"AddLine","points":[[19.37548828125,219.2239084243774]]},{"type":"CloseSubpath"},{"type":"MoveToPoint","points":[[19.37548828125,21.08526611328125]]}],"windingRule":0,"lineJoinStyle":0,"miterLimit":10},"isBackgroundTexture":true,"textBaseline":0,"isVerticalText":false,"textureType":5},"initialState":{"affineTransform":[1,0,0,1,0,0],"masksToBounds":false,"rotation":0,"scale":1,"position":{"pointX":252.12451171875,"pointY":99.41473388671875},"width":543,"sublayerTransform":[1,0,0,0,0,1,0,0,0,0,1,0,0,0,0,1],"contentsRect":{"y":0,"x":0,"width":1,"height":1},"opacity":1,"edgeAntialiasingMask":0,"height":241,"hidden":true,"anchorPoint":{"pointX":0.5,"pointY":0.5}},"texture":"FB324C4DDB5BB68F728CB212B42EF667"}]}]},{"animations":[],"initialState":{"affineTransform":[1,0,0,1,0,0],"masksToBounds":false,"rotation":0,"scale":1,"position":{"pointX":960,"pointY":540},"width":1920,"sublayerTransform":[1,0,0,0,0,1,0,0,0,0,1,0,0,0,0,1],"contentsRect":{"y":0,"x":0,"width":1,"height":1},"opacity":1,"edgeAntialiasingMask":251658240,"height":1080,"hidden":false,"anchorPoint":{"pointX":0.5,"pointY":0.5}},"layers":[{"animations":[],"initialState":{"affineTransform":[1,0,0,1,0,0],"masksToBounds":false,"rotation":0,"scale":1,"position":{"pointX":412.3919677734375,"pointY":422.8253173828125},"width":85.528564453125,"sublayerTransform":[1,0,0,0,0,1,0,0,0,0,1,0,0,0,0,1],"contentsRect":{"y":0,"x":0,"width":1,"height":1},"opacity":1,"edgeAntialiasingMask":251658240,"height":37.474365234375,"hidden":false,"anchorPoint":{"pointX":0.5,"pointY":0.5}},"objectID":"224F0EA6-4DED-48C6-AF55-B891073B9FC3","layers":[{"animations":[],"layers":[],"texturedRectangle":{"singleTextureOpacity":1,"textXHeight":0,"shapePath":{"lineWidth":1,"flatness":0.6,"lineCapStyle":0,"elements":[{"type":"MoveToPoint","points":[[52.23125076293945,31.82121568629373]]},{"type":"AddLine","points":[[52.23125076293945,44.5625]]},{"type":"AddLine","points":[[91.15625,25.8253173828125]]},{"type":"AddLine","points":[[52.23125076293945,7.088134765625]]},{"type":"AddLine","points":[[52.23125076293945,19.82941907933127]]},{"type":"AddLine","points":[[5.627685546875,19.82941907933127]]},{"type":"AddLine","points":[[5.627685546875,31.82121568629373]]},{"type":"CloseSubpath"},{"type":"MoveToPoint","points":[[52.23125076293945,31.82121568629373]]}],"windingRule":0,"lineJoinStyle":0,"miterLimit":10},"isBackgroundTexture":true,"textBaseline":0,"isVerticalText":false,"textureType":5},"initialState":{"affineTransform":[1,0,0,1,0,0],"masksToBounds":false,"rotation":0,"scale":1,"position":{"pointX":42.872314453125,"pointY":18.911865234375},"width":97,"sublayerTransform":[1,0,0,0,0,1,0,0,0,0,1,0,0,0,0,1],"contentsRect":{"y":0,"x":0,"width":1,"height":1},"opacity":1,"edgeAntialiasingMask":0,"height":52,"hidden":true,"anchorPoint":{"pointX":0.5,"pointY":0.5}},"texture":"F103F82652D757B9580E25359DE65B05"}]}]},{"animations":[],"initialState":{"affineTransform":[1,0,0,1,0,0],"masksToBounds":false,"rotation":0,"scale":1,"position":{"pointX":960,"pointY":540},"width":1920,"sublayerTransform":[1,0,0,0,0,1,0,0,0,0,1,0,0,0,0,1],"contentsRect":{"y":0,"x":0,"width":1,"height":1},"opacity":1,"edgeAntialiasingMask":251658240,"height":1080,"hidden":false,"anchorPoint":{"pointX":0.5,"pointY":0.5}},"layers":[{"animations":[],"initialState":{"affineTransform":[1,0,0,1,0,0],"masksToBounds":false,"rotation":0,"scale":1,"position":{"pointX":1417.860717773438,"pointY":498.7628173828125},"width":85.528564453125,"sublayerTransform":[1,0,0,0,0,1,0,0,0,0,1,0,0,0,0,1],"contentsRect":{"y":0,"x":0,"width":1,"height":1},"opacity":1,"edgeAntialiasingMask":251658240,"height":37.474365234375,"hidden":false,"anchorPoint":{"pointX":0.5,"pointY":0.5}},"objectID":"F89DFC79-0A12-4877-8319-F35C27C35ACC","layers":[{"animations":[],"layers":[],"texturedRectangle":{"singleTextureOpacity":1,"textXHeight":0,"shapePath":{"lineWidth":1,"flatness":0.6,"lineCapStyle":0,"elements":[{"type":"MoveToPoint","points":[[51.70000076293945,31.75871568629373]]},{"type":"AddLine","points":[[51.70000076293945,44.5]]},{"type":"AddLine","points":[[90.625,25.7628173828125]]},{"type":"AddLine","points":[[51.70000076293945,7.025634765625]]},{"type":"AddLine","points":[[51.70000076293945,19.76691907933127]]},{"type":"AddLine","points":[[5.096435546875,19.76691907933127]]},{"type":"AddLine","points":[[5.096435546875,31.75871568629373]]},{"type":"CloseSubpath"},{"type":"MoveToPoint","points":[[51.70000076293945,31.75871568629373]]}],"windingRule":0,"lineJoinStyle":0,"miterLimit":10},"isBackgroundTexture":true,"textBaseline":0,"isVerticalText":false,"textureType":5},"initialState":{"affineTransform":[1,0,0,1,0,0],"masksToBounds":false,"rotation":0,"scale":1,"position":{"pointX":42.903564453125,"pointY":18.974365234375},"width":96,"sublayerTransform":[1,0,0,0,0,1,0,0,0,0,1,0,0,0,0,1],"contentsRect":{"y":0,"x":0,"width":1,"height":1},"opacity":1,"edgeAntialiasingMask":0,"height":52,"hidden":true,"anchorPoint":{"pointX":0.5,"pointY":0.5}},"texture":"A39890CA799CAA1EBF0B9EE97BE370DD"}]}]},{"animations":[],"initialState":{"affineTransform":[1,0,0,1,0,0],"masksToBounds":false,"rotation":0,"scale":1,"position":{"pointX":960,"pointY":540},"width":1920,"sublayerTransform":[1,0,0,0,0,1,0,0,0,0,1,0,0,0,0,1],"contentsRect":{"y":0,"x":0,"width":1,"height":1},"opacity":1,"edgeAntialiasingMask":251658240,"height":1080,"hidden":false,"anchorPoint":{"pointX":0.5,"pointY":0.5}},"layers":[{"animations":[],"initialState":{"affineTransform":[1,0,0,1,0,0],"masksToBounds":false,"rotation":0,"scale":1,"position":{"pointX":878.8294677734375,"pointY":679.7315673828125},"width":85.528564453125,"sublayerTransform":[1,0,0,0,0,1,0,0,0,0,1,0,0,0,0,1],"contentsRect":{"y":0,"x":0,"width":1,"height":1},"opacity":1,"edgeAntialiasingMask":251658240,"height":37.474365234375,"hidden":false,"anchorPoint":{"pointX":0.5,"pointY":0.5}},"objectID":"77840946-1951-4B22-A97E-947F818B7BEB","layers":[{"animations":[],"layers":[],"texturedRectangle":{"singleTextureOpacity":1,"textXHeight":0,"shapePath":{"lineWidth":1,"flatness":0.6,"lineCapStyle":0,"elements":[{"type":"MoveToPoint","points":[[51.66875076293945,32.72746568629373]]},{"type":"AddLine","points":[[51.66875076293945,45.46875]]},{"type":"AddLine","points":[[90.59375,26.7315673828125]]},{"type":"AddLine","points":[[51.66875076293945,7.994384765625]]},{"type":"AddLine","points":[[51.66875076293945,20.73566907933127]]},{"type":"AddLine","points":[[5.065185546875,20.73566907933127]]},{"type":"AddLine","points":[[5.065185546875,32.72746568629373]]},{"type":"CloseSubpath"},{"type":"MoveToPoint","points":[[51.66875076293945,32.72746568629373]]}],"windingRule":0,"lineJoinStyle":0,"miterLimit":10},"isBackgroundTexture":true,"textBaseline":0,"isVerticalText":false,"textureType":5},"initialState":{"affineTransform":[1,0,0,1,0,0],"masksToBounds":false,"rotation":0,"scale":1,"position":{"pointX":42.934814453125,"pointY":18.505615234375},"width":96,"sublayerTransform":[1,0,0,0,0,1,0,0,0,0,1,0,0,0,0,1],"contentsRect":{"y":0,"x":0,"width":1,"height":1},"opacity":1,"edgeAntialiasingMask":0,"height":53,"hidden":true,"anchorPoint":{"pointX":0.5,"pointY":0.5}},"texture":"0DB6C110A922BC749D0CD1B6CECD6B2C"}]}]},{"animations":[],"initialState":{"affineTransform":[1,0,0,1,0,0],"masksToBounds":false,"rotation":0,"scale":1,"position":{"pointX":960,"pointY":540},"width":1920,"sublayerTransform":[1,0,0,0,0,1,0,0,0,0,1,0,0,0,0,1],"contentsRect":{"y":0,"x":0,"width":1,"height":1},"opacity":1,"edgeAntialiasingMask":251658240,"height":1080,"hidden":false,"anchorPoint":{"pointX":0.5,"pointY":0.5}},"layers":[{"animations":[],"initialState":{"affineTransform":[1,0,0,1,0,0],"masksToBounds":false,"rotation":0,"scale":1,"position":{"pointX":53.18893432617188,"pointY":53.18893432617188},"width":106.3778686523438,"sublayerTransform":[1,0,0,0,0,1,0,0,0,0,1,0,0,0,0,1],"contentsRect":{"y":0,"x":0,"width":1,"height":1},"opacity":1,"edgeAntialiasingMask":251658240,"height":106.3778686523438,"hidden":false,"anchorPoint":{"pointX":0.5,"pointY":0.5}},"objectID":"9DF650DA-85FF-4A89-9439-7131CE974892","layers":[{"animations":[],"layers":[],"texturedRectangle":{"isBackgroundTexture":true,"singleTextureOpacity":1,"textureType":5,"textBaseline":0,"textXHeight":0,"isVerticalText":false},"initialState":{"affineTransform":[1,0,0,1,0,0],"masksToBounds":false,"rotation":0,"scale":1,"position":{"pointX":53.5,"pointY":53.5},"width":109,"sublayerTransform":[1,0,0,0,0,1,0,0,0,0,1,0,0,0,0,1],"contentsRect":{"y":0,"x":0,"width":1,"height":1},"opacity":1,"edgeAntialiasingMask":0,"height":109,"hidden":false,"anchorPoint":{"pointX":0.5,"pointY":0.5}},"texture":"0AFD695DF00B56CFBA35BE358E1C9D6B"}]}]},{"animations":[],"initialState":{"affineTransform":[1,0,0,1,0,0],"masksToBounds":false,"rotation":0,"scale":1,"position":{"pointX":960,"pointY":540},"width":1920,"sublayerTransform":[1,0,0,0,0,1,0,0,0,0,1,0,0,0,0,1],"contentsRect":{"y":0,"x":0,"width":1,"height":1},"opacity":1,"edgeAntialiasingMask":251658240,"height":1080,"hidden":false,"anchorPoint":{"pointX":0.5,"pointY":0.5}},"layers":[{"animations":[],"initialState":{"affineTransform":[1,0,0,1,0,0],"masksToBounds":false,"rotation":0,"scale":1,"position":{"pointX":84.97068786621094,"pointY":1029.642951965332},"width":150.0625,"sublayerTransform":[1,0,0,0,0,1,0,0,0,0,1,0,0,0,0,1],"contentsRect":{"y":0,"x":0,"width":1,"height":1},"opacity":1,"edgeAntialiasingMask":251658240,"height":78.66712951660156,"hidden":false,"anchorPoint":{"pointX":0.5,"pointY":0.5}},"objectID":"69A5A788-181A-477C-9D91-04F6D73E817D","layers":[{"animations":[],"layers":[],"texturedRectangle":{"isBackgroundTexture":true,"singleTextureOpacity":1,"textureType":5,"textBaseline":0,"textXHeight":0,"isVerticalText":false},"initialState":{"affineTransform":[1,0,0,1,0,0],"masksToBounds":false,"rotation":0,"scale":1,"position":{"pointX":75.06056213378906,"pointY":39.19061279296875},"width":154,"sublayerTransform":[1,0,0,0,0,1,0,0,0,0,1,0,0,0,0,1],"contentsRect":{"y":0,"x":0,"width":1,"height":1},"opacity":1,"edgeAntialiasingMask":0,"height":81,"hidden":false,"anchorPoint":{"pointX":0.5,"pointY":0.5}},"texture":"0A76BA58503224FEEDCA4872F8618A58"}]}]},{"animations":[],"initialState":{"affineTransform":[1,0,0,1,0,0],"masksToBounds":false,"rotation":0,"scale":1,"position":{"pointX":960,"pointY":540},"width":1920,"sublayerTransform":[1,0,0,0,0,1,0,0,0,0,1,0,0,0,0,1],"contentsRect":{"y":0,"x":0,"width":1,"height":1},"opacity":1,"edgeAntialiasingMask":251658240,"height":1080,"hidden":false,"anchorPoint":{"pointX":0.5,"pointY":0.5}},"layers":[{"animations":[],"initialState":{"affineTransform":[1,0,0,1,0,0],"masksToBounds":false,"rotation":0,"scale":1,"position":{"pointX":1823.240089416504,"pointY":1029.475103378296},"width":149.7072296142578,"sublayerTransform":[1,0,0,0,0,1,0,0,0,0,1,0,0,0,0,1],"contentsRect":{"y":0,"x":0,"width":1,"height":1},"opacity":1,"edgeAntialiasingMask":251658240,"height":61.6969108581543,"hidden":false,"anchorPoint":{"pointX":0.5,"pointY":0.5}},"objectID":"03823446-722D-4302-AB95-2B53C52CF60E","layers":[{"animations":[],"layers":[],"texturedRectangle":{"isBackgroundTexture":true,"singleTextureOpacity":1,"textureType":5,"textBaseline":0,"textXHeight":0,"isVerticalText":false},"initialState":{"affineTransform":[1,0,0,1,0,0],"masksToBounds":false,"rotation":0,"scale":1,"position":{"pointX":75.113525390625,"pointY":30.87335205078125},"width":153,"sublayerTransform":[1,0,0,0,0,1,0,0,0,0,1,0,0,0,0,1],"contentsRect":{"y":0,"x":0,"width":1,"height":1},"opacity":1,"edgeAntialiasingMask":0,"height":65,"hidden":false,"anchorPoint":{"pointX":0.5,"pointY":0.5}},"texture":"F1E4F471EFBCA02A7A50F8183033FDEE"}]}]},{"animations":[],"initialState":{"affineTransform":[1,0,0,1,0,0],"masksToBounds":false,"rotation":0,"scale":1,"position":{"pointX":960,"pointY":540},"width":1920,"sublayerTransform":[1,0,0,0,0,1,0,0,0,0,1,0,0,0,0,1],"contentsRect":{"y":0,"x":0,"width":1,"height":1},"opacity":1,"edgeAntialiasingMask":251658240,"height":1080,"hidden":false,"anchorPoint":{"pointX":0.5,"pointY":0.5}},"layers":[{"animations":[],"initialState":{"affineTransform":[1,0,0,1,0,0],"masksToBounds":false,"rotation":0,"scale":1,"position":{"pointX":1809.381950378418,"pointY":53.18893432617188},"width":166.3303070068359,"sublayerTransform":[1,0,0,0,0,1,0,0,0,0,1,0,0,0,0,1],"contentsRect":{"y":0,"x":0,"width":1,"height":1},"opacity":1,"edgeAntialiasingMask":251658240,"height":77.56935119628906,"hidden":false,"anchorPoint":{"pointX":0.5,"pointY":0.5}},"objectID":"F0CB2D3B-746D-4175-BEA3-CF2AAE4A4ACD","layers":[{"animations":[],"layers":[],"texturedRectangle":{"isBackgroundTexture":true,"singleTextureOpacity":1,"textureType":5,"textBaseline":0,"textXHeight":0,"isVerticalText":false},"initialState":{"affineTransform":[1,0,0,1,0,0],"masksToBounds":false,"rotation":0,"scale":1,"position":{"pointX":83.283203125,"pointY":38.59574127197266},"width":169,"sublayerTransform":[1,0,0,0,0,1,0,0,0,0,1,0,0,0,0,1],"contentsRect":{"y":0,"x":0,"width":1,"height":1},"opacity":1,"edgeAntialiasingMask":0,"height":80,"hidden":false,"anchorPoint":{"pointX":0.5,"pointY":0.5}},"texture":"3A6AA7E13049CA43A0D406F83530A09D"}]}]}]}},{"effects":[{"beginTime":0,"baseLayer":{"animations":[],"initialState":{"affineTransform":[1,0,0,1,0,0],"masksToBounds":false,"rotation":0,"scale":1,"position":{"pointX":1388.788191229105,"pointY":841.1545858383179},"width":504.38790589571,"sublayerTransform":[1,0,0,0,0,1,0,0,0,0,1,0,0,0,0,1],"contentsRect":{"y":0,"x":0,"width":1,"height":1},"opacity":1,"edgeAntialiasingMask":251658240,"height":401.1777019500732,"hidden":false,"anchorPoint":{"pointX":0.5,"pointY":0.5}},"objectID":"0E6961F4-4873-41F8-8151-E74DAD01F4EF","layers":[{"animations":[],"initialState":{"affineTransform":[1,0,0,1,0,0],"masksToBounds":false,"rotation":0,"scale":1,"position":{"pointX":-176.59423828125,"pointY":-100.5657348632812},"width":504.38790589571,"sublayerTransform":[1,0,0,0,0,1,0,0,0,0,1,-0.0003500791246677598,0,0,0,1],"contentsRect":{"y":0,"x":0,"width":1,"height":1},"opacity":1,"edgeAntialiasingMask":251658240,"height":401.1777019500732,"hidden":false,"anchorPoint":{"pointX":-0.3501159250986553,"pointY":-0.2506762822919722}},"layers":[{"animations":[{"timeOffset":0,"beginTime":1e-100,"repeatCount":0,"animations":[{"timeOffset":0,"from":{"scalar":1},"beginTime":0,"repeatCount":0,"fillMode":"both","duration":1,"autoreverses":false,"timingFunction":"EaseInEaseOut","property":"opacity","to":{"scalar":0}}],"fillMode":"both","autoreverses":false,"duration":1}],"layers":[],"texturedRectangle":{"singleTextureOpacity":1,"textXHeight":0,"shapePath":{"lineWidth":1,"flatness":0.6,"lineCapStyle":0,"elements":[{"type":"MoveToPoint","points":[[19.59423828125,21.56573486328125]]},{"type":"AddLine","points":[[523.98214417696,21.56573486328125]]},{"type":"AddLine","points":[[523.98214417696,422.7434368133545]]},{"type":"AddLine","points":[[19.59423828125,422.7434368133545]]},{"type":"CloseSubpath"},{"type":"MoveToPoint","points":[[19.59423828125,21.56573486328125]]}],"windingRule":0,"lineJoinStyle":0,"miterLimit":10},"isBackgroundTexture":true,"textBaseline":0,"isVerticalText":false,"textureType":5},"initialState":{"affineTransform":[1,0,0,1,0,0],"masksToBounds":false,"rotation":0,"scale":1,"position":{"pointX":251.90576171875,"pointY":200.4342651367188},"width":543,"sublayerTransform":[1,0,0,0,0,1,0,0,0,0,1,0,0,0,0,1],"contentsRect":{"y":0,"x":0,"width":1,"height":1},"opacity":1,"edgeAntialiasingMask":0,"height":444,"hidden":false,"anchorPoint":{"pointX":0.5,"pointY":0.5}},"texture":"28AB14DD929655C84A34F48A511892A5"}]}]},"effects":[],"duration":1,"type":"buildOut","name":"apple:dissolve character","objectID":"0E6961F4-4873-41F8-8151-E74DAD01F4EF"},{"beginTime":0,"baseLayer":{"animations":[],"initialState":{"affineTransform":[1,0,0,1,0,0],"masksToBounds":false,"rotation":0,"scale":1,"position":{"pointX":529.569441229105,"pointY":841.1545872688293},"width":504.38790589571,"sublayerTransform":[1,0,0,0,0,1,0,0,0,0,1,0,0,0,0,1],"contentsRect":{"y":0,"x":0,"width":1,"height":1},"opacity":1,"edgeAntialiasingMask":251658240,"height":198.1386423110962,"hidden":false,"anchorPoint":{"pointX":0.5,"pointY":0.5}},"objectID":"D6F34A34-5201-48E8-B6AB-52BCCE77C11C","layers":[{"animations":[],"initialState":{"affineTransform":[1,0,0,1,0,0],"masksToBounds":false,"rotation":0,"scale":1,"position":{"pointX":682.62451171875,"pointY":-202.0852661132812},"width":504.38790589571,"sublayerTransform":[1,0,0,0,0,1,0,0,0,0,1,-0.0003500791246677598,0,0,0,1],"contentsRect":{"y":0,"x":0,"width":1,"height":1},"opacity":1,"edgeAntialiasingMask":251658240,"height":198.1386423110962,"hidden":false,"anchorPoint":{"pointX":1.353372084738077,"pointY":-1.019918496241579}},"layers":[{"animations":[{"timeOffset":0,"beginTime":1e-100,"repeatCount":0,"animations":[{"timeOffset":0,"from":{"scalar":0},"beginTime":0,"repeatCount":0,"fillMode":"both","duration":1,"autoreverses":false,"timingFunction":"EaseInEaseOut","property":"opacity","to":{"scalar":1}},{"timeOffset":0,"from":{"scalar":false},"beginTime":0,"repeatCount":0,"fillMode":"forwards","property":"hidden","autoreverses":false,"duration":1,"to":{"scalar":false}}],"fillMode":"both","autoreverses":false,"duration":1}],"layers":[],"texturedRectangle":{"singleTextureOpacity":1,"textXHeight":0,"shapePath":{"lineWidth":1,"flatness":0.6,"lineCapStyle":0,"elements":[{"type":"MoveToPoint","points":[[19.37548828125,21.08526611328125]]},{"type":"AddLine","points":[[523.76339417696,21.08526611328125]]},{"type":"AddLine","points":[[523.76339417696,219.2239084243774]]},{"type":"AddLine","points":[[19.37548828125,219.2239084243774]]},{"type":"CloseSubpath"},{"type":"MoveToPoint","points":[[19.37548828125,21.08526611328125]]}],"windingRule":0,"lineJoinStyle":0,"miterLimit":10},"isBackgroundTexture":true,"textBaseline":0,"isVerticalText":false,"textureType":5},"initialState":{"affineTransform":[1,0,0,1,0,0],"masksToBounds":false,"rotation":0,"scale":1,"position":{"pointX":252.12451171875,"pointY":99.41473388671875},"width":543,"sublayerTransform":[1,0,0,0,0,1,0,0,0,0,1,0,0,0,0,1],"contentsRect":{"y":0,"x":0,"width":1,"height":1},"opacity":1,"edgeAntialiasingMask":0,"height":241,"hidden":true,"anchorPoint":{"pointX":0.5,"pointY":0.5}},"texture":"FB324C4DDB5BB68F728CB212B42EF667"}]}]},"effects":[{"beginTime":0,"baseLayer":{"animations":[],"initialState":{"affineTransform":[1,0,0,1,0,0],"masksToBounds":false,"rotation":0,"scale":1,"position":{"pointX":412.3919677734375,"pointY":422.8253173828125},"width":85.528564453125,"sublayerTransform":[1,0,0,0,0,1,0,0,0,0,1,0,0,0,0,1],"contentsRect":{"y":0,"x":0,"width":1,"height":1},"opacity":1,"edgeAntialiasingMask":251658240,"height":37.474365234375,"hidden":false,"anchorPoint":{"pointX":0.5,"pointY":0.5}},"objectID":"224F0EA6-4DED-48C6-AF55-B891073B9FC3","layers":[{"animations":[],"initialState":{"affineTransform":[1,0,0,1,0,0],"masksToBounds":false,"rotation":0,"scale":1,"position":{"pointX":590.372314453125,"pointY":135.911865234375},"width":85.528564453125,"sublayerTransform":[1,0,0,0,0,1,0,0,0,0,1,-0.0003500791246677598,0,0,0,1],"contentsRect":{"y":0,"x":0,"width":1,"height":1},"opacity":1,"edgeAntialiasingMask":251658240,"height":37.474365234375,"hidden":false,"anchorPoint":{"pointX":6.902633269107257,"pointY":3.626795661096453}},"layers":[{"animations":[{"timeOffset":0,"beginTime":1e-100,"repeatCount":0,"animations":[{"timeOffset":0,"from":{"scalar":0},"beginTime":0,"repeatCount":0,"fillMode":"both","duration":0.5,"autoreverses":false,"timingFunction":"EaseInEaseOut","property":"opacity","to":{"scalar":1}},{"timeOffset":0,"from":{"scalar":false},"beginTime":0,"repeatCount":0,"fillMode":"forwards","property":"hidden","autoreverses":false,"duration":0.5,"to":{"scalar":false}}],"fillMode":"both","autoreverses":false,"duration":0.5}],"layers":[],"texturedRectangle":{"singleTextureOpacity":1,"textXHeight":0,"shapePath":{"lineWidth":1,"flatness":0.6,"lineCapStyle":0,"elements":[{"type":"MoveToPoint","points":[[52.23125076293945,31.82121568629373]]},{"type":"AddLine","points":[[52.23125076293945,44.5625]]},{"type":"AddLine","points":[[91.15625,25.8253173828125]]},{"type":"AddLine","points":[[52.23125076293945,7.088134765625]]},{"type":"AddLine","points":[[52.23125076293945,19.82941907933127]]},{"type":"AddLine","points":[[5.627685546875,19.82941907933127]]},{"type":"AddLine","points":[[5.627685546875,31.82121568629373]]},{"type":"CloseSubpath"},{"type":"MoveToPoint","points":[[52.23125076293945,31.82121568629373]]}],"windingRule":0,"lineJoinStyle":0,"miterLimit":10},"isBackgroundTexture":true,"textBaseline":0,"isVerticalText":false,"textureType":5},"initialState":{"affineTransform":[1,0,0,1,0,0],"masksToBounds":false,"rotation":0,"scale":1,"position":{"pointX":42.872314453125,"pointY":18.911865234375},"width":97,"sublayerTransform":[1,0,0,0,0,1,0,0,0,0,1,0,0,0,0,1],"contentsRect":{"y":0,"x":0,"width":1,"height":1},"opacity":1,"edgeAntialiasingMask":0,"height":52,"hidden":true,"anchorPoint":{"pointX":0.5,"pointY":0.5}},"texture":"F103F82652D757B9580E25359DE65B05"}]}]},"effects":[],"duration":0.5,"type":"buildIn","attributes":{"direction":0},"name":"com.apple.iWork.Keynote.FromDarkness","objectID":"224F0EA6-4DED-48C6-AF55-B891073B9FC3"},{"beginTime":0,"baseLayer":{"animations":[],"initialState":{"affineTransform":[1,0,0,1,0,0],"masksToBounds":false,"rotation":0,"scale":1,"position":{"pointX":1417.860717773438,"pointY":498.7628173828125},"width":85.528564453125,"sublayerTransform":[1,0,0,0,0,1,0,0,0,0,1,0,0,0,0,1],"contentsRect":{"y":0,"x":0,"width":1,"height":1},"opacity":1,"edgeAntialiasingMask":251658240,"height":37.474365234375,"hidden":false,"anchorPoint":{"pointX":0.5,"pointY":0.5}},"objectID":"F89DFC79-0A12-4877-8319-F35C27C35ACC","layers":[{"animations":[],"initialState":{"affineTransform":[1,0,0,1,0,0],"masksToBounds":false,"rotation":0,"scale":1,"position":{"pointX":-415.096435546875,"pointY":59.974365234375},"width":85.528564453125,"sublayerTransform":[1,0,0,0,0,1,0,0,0,0,1,-0.0003500791246677598,0,0,0,1],"contentsRect":{"y":0,"x":0,"width":1,"height":1},"opacity":1,"edgeAntialiasingMask":251658240,"height":37.474365234375,"hidden":false,"anchorPoint":{"pointX":-4.853307642903019,"pointY":1.600410436822046}},"layers":[{"animations":[{"timeOffset":0,"beginTime":1e-100,"repeatCount":0,"animations":[{"timeOffset":0,"from":{"scalar":0},"beginTime":0,"repeatCount":0,"fillMode":"both","duration":0.5,"autoreverses":false,"timingFunction":"EaseInEaseOut","property":"opacity","to":{"scalar":1}},{"timeOffset":0,"from":{"scalar":false},"beginTime":0,"repeatCount":0,"fillMode":"forwards","property":"hidden","autoreverses":false,"duration":0.5,"to":{"scalar":false}}],"fillMode":"both","autoreverses":false,"duration":0.5}],"layers":[],"texturedRectangle":{"singleTextureOpacity":1,"textXHeight":0,"shapePath":{"lineWidth":1,"flatness":0.6,"lineCapStyle":0,"elements":[{"type":"MoveToPoint","points":[[51.70000076293945,31.75871568629373]]},{"type":"AddLine","points":[[51.70000076293945,44.5]]},{"type":"AddLine","points":[[90.625,25.7628173828125]]},{"type":"AddLine","points":[[51.70000076293945,7.025634765625]]},{"type":"AddLine","points":[[51.70000076293945,19.76691907933127]]},{"type":"AddLine","points":[[5.096435546875,19.76691907933127]]},{"type":"AddLine","points":[[5.096435546875,31.75871568629373]]},{"type":"CloseSubpath"},{"type":"MoveToPoint","points":[[51.70000076293945,31.75871568629373]]}],"windingRule":0,"lineJoinStyle":0,"miterLimit":10},"isBackgroundTexture":true,"textBaseline":0,"isVerticalText":false,"textureType":5},"initialState":{"affineTransform":[1,0,0,1,0,0],"masksToBounds":false,"rotation":0,"scale":1,"position":{"pointX":42.903564453125,"pointY":18.974365234375},"width":96,"sublayerTransform":[1,0,0,0,0,1,0,0,0,0,1,0,0,0,0,1],"contentsRect":{"y":0,"x":0,"width":1,"height":1},"opacity":1,"edgeAntialiasingMask":0,"height":52,"hidden":true,"anchorPoint":{"pointX":0.5,"pointY":0.5}},"texture":"A39890CA799CAA1EBF0B9EE97BE370DD"}]}]},"effects":[],"duration":0.5,"type":"buildIn","attributes":{"direction":0},"name":"com.apple.iWork.Keynote.FromDarkness","objectID":"F89DFC79-0A12-4877-8319-F35C27C35ACC"},{"beginTime":0,"baseLayer":{"animations":[],"initialState":{"affineTransform":[1,0,0,1,0,0],"masksToBounds":false,"rotation":0,"scale":1,"position":{"pointX":878.8294677734375,"pointY":679.7315673828125},"width":85.528564453125,"sublayerTransform":[1,0,0,0,0,1,0,0,0,0,1,0,0,0,0,1],"contentsRect":{"y":0,"x":0,"width":1,"height":1},"opacity":1,"edgeAntialiasingMask":251658240,"height":37.474365234375,"hidden":false,"anchorPoint":{"pointX":0.5,"pointY":0.5}},"objectID":"77840946-1951-4B22-A97E-947F818B7BEB","layers":[{"animations":[],"initialState":{"affineTransform":[1,0,0,1,0,0],"masksToBounds":false,"rotation":0,"scale":1,"position":{"pointX":123.934814453125,"pointY":-120.994384765625},"width":85.528564453125,"sublayerTransform":[1,0,0,0,0,1,0,0,0,0,1,-0.0003500791246677598,0,0,0,1],"contentsRect":{"y":0,"x":0,"width":1,"height":1},"opacity":1,"edgeAntialiasingMask":251658240,"height":37.474365234375,"hidden":false,"anchorPoint":{"pointX":1.449045885963034,"pointY":-3.228724062673051}},"layers":[{"animations":[{"timeOffset":0,"beginTime":1e-100,"repeatCount":0,"animations":[{"timeOffset":0,"from":{"scalar":0},"beginTime":0,"repeatCount":0,"fillMode":"both","duration":0.5,"autoreverses":false,"timingFunction":"EaseInEaseOut","property":"opacity","to":{"scalar":1}},{"timeOffset":0,"from":{"scalar":false},"beginTime":0,"repeatCount":0,"fillMode":"forwards","property":"hidden","autoreverses":false,"duration":0.5,"to":{"scalar":false}}],"fillMode":"both","autoreverses":false,"duration":0.5}],"layers":[],"texturedRectangle":{"singleTextureOpacity":1,"textXHeight":0,"shapePath":{"lineWidth":1,"flatness":0.6,"lineCapStyle":0,"elements":[{"type":"MoveToPoint","points":[[51.66875076293945,32.72746568629373]]},{"type":"AddLine","points":[[51.66875076293945,45.46875]]},{"type":"AddLine","points":[[90.59375,26.7315673828125]]},{"type":"AddLine","points":[[51.66875076293945,7.994384765625]]},{"type":"AddLine","points":[[51.66875076293945,20.73566907933127]]},{"type":"AddLine","points":[[5.065185546875,20.73566907933127]]},{"type":"AddLine","points":[[5.065185546875,32.72746568629373]]},{"type":"CloseSubpath"},{"type":"MoveToPoint","points":[[51.66875076293945,32.72746568629373]]}],"windingRule":0,"lineJoinStyle":0,"miterLimit":10},"isBackgroundTexture":true,"textBaseline":0,"isVerticalText":false,"textureType":5},"initialState":{"affineTransform":[1,0,0,1,0,0],"masksToBounds":false,"rotation":0,"scale":1,"position":{"pointX":42.934814453125,"pointY":18.505615234375},"width":96,"sublayerTransform":[1,0,0,0,0,1,0,0,0,0,1,0,0,0,0,1],"contentsRect":{"y":0,"x":0,"width":1,"height":1},"opacity":1,"edgeAntialiasingMask":0,"height":53,"hidden":true,"anchorPoint":{"pointX":0.5,"pointY":0.5}},"texture":"0DB6C110A922BC749D0CD1B6CECD6B2C"}]}]},"effects":[],"duration":0.5,"type":"buildIn","attributes":{"direction":0},"name":"com.apple.iWork.Keynote.FromDarkness","objectID":"77840946-1951-4B22-A97E-947F818B7BEB"}],"duration":1,"type":"buildIn","attributes":{"direction":0},"name":"com.apple.iWork.Keynote.FromDarkness","objectID":"D6F34A34-5201-48E8-B6AB-52BCCE77C11C"}],"automaticPlay":false,"hyperlinks":[],"accessibility":[{"text":"droppedImage.pdf","targetRectangle":{"y":0,"x":0,"width":106.3778686523438,"height":106.3778686523438}},{"text":"logo_idb_black.png","targetRectangle":{"y":14.40425872802734,"x":1726.216796875,"width":166.3303070068359,"height":77.56935119628906}},{"text":"Waze Social Alerts","targetRectangle":{"y":684.1907348632812,"x":1247.686630249023,"width":282.203125,"height":38}},{"text":"4294 alerts","targetRectangle":{"y":760.1907348632812,"x":1306.053817749023,"width":165.46875,"height":38}},{"text":"Avenida Brasil","targetRectangle":{"y":798.1907348632812,"x":1285.940192749023,"width":205.6959999999999,"height":38}},{"text":"Entre Av. das Missões e","targetRectangle":{"y":836.1907348632812,"x":1218.052192749023,"width":341.4720000000002,"height":38}},{"text":"Presidente Dutra","targetRectangle":{"y":874.1907348632812,"x":1269.044192749024,"width":239.4880000000001,"height":38}},{"text":"Logo Waze Branco.png","targetRectangle":{"y":998.6266479492188,"x":1748.386474609375,"width":149.7072296142578,"height":61.6969108581543}},{"text":"AV. BRASIL / PRESIDENTE DUTRA","targetRectangle":{"y":18.81250262260437,"x":533.1060375509261,"width":853.7880000000004,"height":62.49163818359375}},{"text":"logo_vertical.png","targetRectangle":{"y":990.3093872070312,"x":9.939437866210938,"width":150.0625,"height":78.66712951660156}},{"text":"01-Brasil-Dutra.png","targetRectangle":{"y":1.84375,"x":1,"width":1918,"height":1183.539306640625}}],"baseLayer":{"animations":[],"initialState":{"affineTransform":[1,0,0,1,0,0],"masksToBounds":false,"rotation":0,"scale":1,"position":{"pointX":960,"pointY":540},"width":1920,"sublayerTransform":[1,0,0,0,0,1,0,0,0,0,1,0,0,0,0,1],"contentsRect":{"y":0,"x":0,"width":1,"height":1},"opacity":1,"edgeAntialiasingMask":251658240,"height":1080,"hidden":false,"anchorPoint":{"pointX":0.5,"pointY":0.5}},"layers":[{"animations":[],"initialState":{"affineTransform":[1,0,0,1,0,0],"masksToBounds":false,"rotation":0,"scale":1,"position":{"pointX":960,"pointY":540},"width":1920,"sublayerTransform":[1,0,0,0,0,1,0,0,0,0,1,0,0,0,0,1],"contentsRect":{"y":0,"x":0,"width":1,"height":1},"opacity":1,"edgeAntialiasingMask":251658240,"height":1080,"hidden":false,"anchorPoint":{"pointX":0.5,"pointY":0.5}},"layers":[{"animations":[],"initialState":{"affineTransform":[1,0,0,1,0,0],"masksToBounds":false,"rotation":0,"scale":1,"position":{"pointX":960,"pointY":540},"width":1920,"sublayerTransform":[1,0,0,0,0,1,0,0,0,0,1,0,0,0,0,1],"contentsRect":{"y":0,"x":0,"width":1,"height":1},"opacity":1,"edgeAntialiasingMask":251658240,"height":1080,"hidden":false,"anchorPoint":{"pointX":0.5,"pointY":0.5}},"layers":[{"animations":[],"layers":[],"texturedRectangle":{"isBackgroundTexture":true,"singleTextureOpacity":1,"textureType":1,"textBaseline":0,"textXHeight":0,"isVerticalText":false},"initialState":{"affineTransform":[1,0,0,1,0,0],"masksToBounds":false,"rotation":0,"scale":1,"position":{"pointX":960,"pointY":540},"width":1920,"sublayerTransform":[1,0,0,0,0,1,0,0,0,0,1,0,0,0,0,1],"contentsRect":{"y":0,"x":0,"width":1,"height":1},"opacity":1,"edgeAntialiasingMask":0,"height":1080,"hidden":false,"anchorPoint":{"pointX":0.5,"pointY":0.5}},"texture":"C25C25FF361FB24FC35F6B120D2F252D"}]}]},{"animations":[],"initialState":{"affineTransform":[1,0,0,1,0,0],"masksToBounds":false,"rotation":0,"scale":1,"position":{"pointX":960,"pointY":540},"width":1920,"sublayerTransform":[1,0,0,0,0,1,0,0,0,0,1,0,0,0,0,1],"contentsRect":{"y":0,"x":0,"width":1,"height":1},"opacity":1,"edgeAntialiasingMask":251658240,"height":1080,"hidden":false,"anchorPoint":{"pointX":0.5,"pointY":0.5}},"layers":[{"animations":[],"initialState":{"affineTransform":[1,0,0,1,0,0],"masksToBounds":false,"rotation":0,"scale":1,"position":{"pointX":960,"pointY":593.6134033203125},"width":1918,"sublayerTransform":[1,0,0,0,0,1,0,0,0,0,1,0,0,0,0,1],"contentsRect":{"y":0,"x":0,"width":1,"height":1},"opacity":1,"edgeAntialiasingMask":251658240,"height":1183.539306640625,"hidden":false,"anchorPoint":{"pointX":0.5,"pointY":0.5}},"objectID":"78B5E340-7EF1-464F-88CE-D000F6A0C81E","layers":[{"animations":[],"layers":[],"texturedRectangle":{"isBackgroundTexture":true,"singleTextureOpacity":1,"textureType":5,"textBaseline":0,"textXHeight":0,"isVerticalText":false},"initialState":{"affineTransform":[1,0,0,1,0,0],"masksToBounds":false,"rotation":0,"scale":1,"position":{"pointX":959,"pointY":591.65625},"width":1920,"sublayerTransform":[1,0,0,0,0,1,0,0,0,0,1,0,0,0,0,1],"contentsRect":{"y":0,"x":0,"width":1,"height":1},"opacity":1,"edgeAntialiasingMask":0,"height":1187,"hidden":false,"anchorPoint":{"pointX":0.5,"pointY":0.5}},"texture":"BDB8E63E646B8A3223E470DDFAFD49BB"}]}]},{"animations":[],"initialState":{"affineTransform":[1,0,0,1,0,0],"masksToBounds":false,"rotation":0,"scale":1,"position":{"pointX":960,"pointY":540},"width":1920,"sublayerTransform":[1,0,0,0,0,1,0,0,0,0,1,0,0,0,0,1],"contentsRect":{"y":0,"x":0,"width":1,"height":1},"opacity":1,"edgeAntialiasingMask":251658240,"height":1080,"hidden":false,"anchorPoint":{"pointX":0.5,"pointY":0.5}},"layers":[{"animations":[],"initialState":{"affineTransform":[1,0,0,1,0,0],"masksToBounds":false,"rotation":0,"scale":1,"position":{"pointX":960.0000165700912,"pointY":50.37643754482269},"width":1919.218585968018,"sublayerTransform":[1,0,0,0,0,1,0,0,0,0,1,0,0,0,0,1],"contentsRect":{"y":0,"x":0,"width":1,"height":1},"opacity":1,"edgeAntialiasingMask":251658240,"height":106.3778698444366,"hidden":false,"anchorPoint":{"pointX":0.5,"pointY":0.5}},"objectID":"BF198EBE-308C-465F-90FB-70B7657CE152","layers":[{"animations":[],"layers":[],"texturedRectangle":{"singleTextureOpacity":1,"textXHeight":0,"shapePath":{"lineWidth":1,"flatness":0.6,"lineCapStyle":0,"elements":[{"type":"MoveToPoint","points":[[1.390723586082458,1.18750262260437]]},{"type":"AddLine","points":[[1920.6093095541,1.18750262260437]]},{"type":"AddLine","points":[[1920.6093095541,107.565372467041]]},{"type":"AddLine","points":[[1.390723586082458,107.565372467041]]},{"type":"CloseSubpath"},{"type":"MoveToPoint","points":[[1.390723586082458,1.18750262260437]]}],"windingRule":0,"lineJoinStyle":0,"miterLimit":10},"isBackgroundTexture":true,"textBaseline":0,"isVerticalText":false,"textureType":5},"initialState":{"affineTransform":[1,0,0,1,0,0],"masksToBounds":false,"rotation":0,"scale":1,"position":{"pointX":959.6092764139175,"pointY":53.31249737739563},"width":1922,"sublayerTransform":[1,0,0,0,0,1,0,0,0,0,1,0,0,0,0,1],"contentsRect":{"y":0,"x":0,"width":1,"height":1},"opacity":1,"edgeAntialiasingMask":0,"height":109,"hidden":false,"anchorPoint":{"pointX":0.5,"pointY":0.5}},"texture":"1FBF80488DA9D9CD43214480320209F2"}]}]},{"animations":[],"initialState":{"affineTransform":[1,0,0,1,0,0],"masksToBounds":false,"rotation":0,"scale":1,"position":{"pointX":960,"pointY":540},"width":1920,"sublayerTransform":[1,0,0,0,0,1,0,0,0,0,1,0,0,0,0,1],"contentsRect":{"y":0,"x":0,"width":1,"height":1},"opacity":1,"edgeAntialiasingMask":251658240,"height":1080,"hidden":false,"anchorPoint":{"pointX":0.5,"pointY":0.5}},"layers":[{"animations":[],"initialState":{"affineTransform":[1,0,0,1,0,0],"masksToBounds":false,"rotation":0,"scale":1,"position":{"pointX":960,"pointY":289.0942358970642},"width":666.454345703125,"sublayerTransform":[1,0,0,0,0,1,0,0,0,0,1,0,0,0,0,1],"contentsRect":{"y":0,"x":0,"width":1,"height":1},"opacity":1,"edgeAntialiasingMask":251658240,"height":249.2924757003784,"hidden":false,"anchorPoint":{"pointX":0.5,"pointY":0.5}},"objectID":"E43A25C0-998F-45E8-BFA1-BCC657B0FCBF","layers":[{"animations":[],"layers":[],"texturedRectangle":{"singleTextureOpacity":1,"textXHeight":0,"shapePath":{"lineWidth":1,"flatness":0.6,"lineCapStyle":0,"elements":[{"type":"MoveToPoint","points":[[568.1523198052309,40.43090961984672]]},{"type":"AddCurve","points":[[696.918790533673,87.741458383809],[696.918790533673,164.4470134103194],[568.1523198052309,211.7575621742817]]},{"type":"AddCurve","points":[[439.3858490767889,259.068110938244],[230.6141509232111,259.068110938244],[101.8476801947691,211.7575621742817]]},{"type":"AddCurve","points":[[-26.91879053367302,164.4470134103194],[-26.91879053367302,87.741458383809],[101.8476801947691,40.43090961984672]]},{"type":"AddCurve","points":[[230.6141509232111,-6.879639144115572],[439.3858490767889,-6.879639144115572],[568.1523198052309,40.43090961984672]]},{"type":"CloseSubpath"},{"type":"MoveToPoint","points":[[568.1523198052309,40.43090961984672]]}],"windingRule":0,"lineJoinStyle":0,"miterLimit":10},"isBackgroundTexture":true,"textBaseline":0,"isVerticalText":false,"textureType":5},"initialState":{"affineTransform":[1,0,0,1,0,0],"masksToBounds":false,"rotation":0,"scale":1,"position":{"pointX":333.2271728515625,"pointY":124.552001953125},"width":670,"sublayerTransform":[1,0,0,0,0,1,0,0,0,0,1,0,0,0,0,1],"contentsRect":{"y":0,"x":0,"width":1,"height":1},"opacity":1,"edgeAntialiasingMask":0,"height":252,"hidden":false,"anchorPoint":{"pointX":0.5,"pointY":0.5}},"texture":"2D6FAE11570D11BD139BBDFCBD5B0B84"}]}]},{"animations":[],"initialState":{"affineTransform":[1,0,0,1,0,0],"masksToBounds":false,"rotation":0,"scale":1,"position":{"pointX":960,"pointY":540},"width":1920,"sublayerTransform":[1,0,0,0,0,1,0,0,0,0,1,0,0,0,0,1],"contentsRect":{"y":0,"x":0,"width":1,"height":1},"opacity":1,"edgeAntialiasingMask":251658240,"height":1080,"hidden":false,"anchorPoint":{"pointX":0.5,"pointY":0.5}},"layers":[{"animations":[],"initialState":{"affineTransform":[1,0,0,1,0,0],"masksToBounds":false,"rotation":0,"scale":1,"position":{"pointX":1388.788191229105,"pointY":841.1545858383179},"width":504.38790589571,"sublayerTransform":[1,0,0,0,0,1,0,0,0,0,1,0,0,0,0,1],"contentsRect":{"y":0,"x":0,"width":1,"height":1},"opacity":1,"edgeAntialiasingMask":251658240,"height":401.1777019500732,"hidden":false,"anchorPoint":{"pointX":0.5,"pointY":0.5}},"objectID":"0E6961F4-4873-41F8-8151-E74DAD01F4EF","layers":[{"animations":[],"layers":[],"texturedRectangle":{"singleTextureOpacity":1,"textXHeight":0,"shapePath":{"lineWidth":1,"flatness":0.6,"lineCapStyle":0,"elements":[{"type":"MoveToPoint","points":[[19.59423828125,21.56573486328125]]},{"type":"AddLine","points":[[523.98214417696,21.56573486328125]]},{"type":"AddLine","points":[[523.98214417696,422.7434368133545]]},{"type":"AddLine","points":[[19.59423828125,422.7434368133545]]},{"type":"CloseSubpath"},{"type":"MoveToPoint","points":[[19.59423828125,21.56573486328125]]}],"windingRule":0,"lineJoinStyle":0,"miterLimit":10},"isBackgroundTexture":true,"textBaseline":0,"isVerticalText":false,"textureType":5},"initialState":{"affineTransform":[1,0,0,1,0,0],"masksToBounds":false,"rotation":0,"scale":1,"position":{"pointX":251.90576171875,"pointY":200.4342651367188},"width":543,"sublayerTransform":[1,0,0,0,0,1,0,0,0,0,1,0,0,0,0,1],"contentsRect":{"y":0,"x":0,"width":1,"height":1},"opacity":1,"edgeAntialiasingMask":0,"height":444,"hidden":false,"anchorPoint":{"pointX":0.5,"pointY":0.5}},"texture":"28AB14DD929655C84A34F48A511892A5"}]}]},{"animations":[],"initialState":{"affineTransform":[1,0,0,1,0,0],"masksToBounds":false,"rotation":0,"scale":1,"position":{"pointX":960,"pointY":540},"width":1920,"sublayerTransform":[1,0,0,0,0,1,0,0,0,0,1,0,0,0,0,1],"contentsRect":{"y":0,"x":0,"width":1,"height":1},"opacity":1,"edgeAntialiasingMask":251658240,"height":1080,"hidden":false,"anchorPoint":{"pointX":0.5,"pointY":0.5}},"layers":[{"animations":[],"initialState":{"affineTransform":[1,0,0,1,0,0],"masksToBounds":false,"rotation":0,"scale":1,"position":{"pointX":529.569441229105,"pointY":841.1545872688293},"width":504.38790589571,"sublayerTransform":[1,0,0,0,0,1,0,0,0,0,1,0,0,0,0,1],"contentsRect":{"y":0,"x":0,"width":1,"height":1},"opacity":1,"edgeAntialiasingMask":251658240,"height":198.1386423110962,"hidden":false,"anchorPoint":{"pointX":0.5,"pointY":0.5}},"objectID":"D6F34A34-5201-48E8-B6AB-52BCCE77C11C","layers":[{"animations":[],"layers":[],"texturedRectangle":{"singleTextureOpacity":1,"textXHeight":0,"shapePath":{"lineWidth":1,"flatness":0.6,"lineCapStyle":0,"elements":[{"type":"MoveToPoint","points":[[19.37548828125,21.08526611328125]]},{"type":"AddLine","points":[[523.76339417696,21.08526611328125]]},{"type":"AddLine","points":[[523.76339417696,219.2239084243774]]},{"type":"AddLine","points":[[19.37548828125,219.2239084243774]]},{"type":"CloseSubpath"},{"type":"MoveToPoint","points":[[19.37548828125,21.08526611328125]]}],"windingRule":0,"lineJoinStyle":0,"miterLimit":10},"isBackgroundTexture":true,"textBaseline":0,"isVerticalText":false,"textureType":5},"initialState":{"affineTransform":[1,0,0,1,0,0],"masksToBounds":false,"rotation":0,"scale":1,"position":{"pointX":252.12451171875,"pointY":99.41473388671875},"width":543,"sublayerTransform":[1,0,0,0,0,1,0,0,0,0,1,0,0,0,0,1],"contentsRect":{"y":0,"x":0,"width":1,"height":1},"opacity":1,"edgeAntialiasingMask":0,"height":241,"hidden":true,"anchorPoint":{"pointX":0.5,"pointY":0.5}},"texture":"FB324C4DDB5BB68F728CB212B42EF667"}]}]},{"animations":[],"initialState":{"affineTransform":[1,0,0,1,0,0],"masksToBounds":false,"rotation":0,"scale":1,"position":{"pointX":960,"pointY":540},"width":1920,"sublayerTransform":[1,0,0,0,0,1,0,0,0,0,1,0,0,0,0,1],"contentsRect":{"y":0,"x":0,"width":1,"height":1},"opacity":1,"edgeAntialiasingMask":251658240,"height":1080,"hidden":false,"anchorPoint":{"pointX":0.5,"pointY":0.5}},"layers":[{"animations":[],"initialState":{"affineTransform":[1,0,0,1,0,0],"masksToBounds":false,"rotation":0,"scale":1,"position":{"pointX":412.3919677734375,"pointY":422.8253173828125},"width":85.528564453125,"sublayerTransform":[1,0,0,0,0,1,0,0,0,0,1,0,0,0,0,1],"contentsRect":{"y":0,"x":0,"width":1,"height":1},"opacity":1,"edgeAntialiasingMask":251658240,"height":37.474365234375,"hidden":false,"anchorPoint":{"pointX":0.5,"pointY":0.5}},"objectID":"224F0EA6-4DED-48C6-AF55-B891073B9FC3","layers":[{"animations":[],"layers":[],"texturedRectangle":{"singleTextureOpacity":1,"textXHeight":0,"shapePath":{"lineWidth":1,"flatness":0.6,"lineCapStyle":0,"elements":[{"type":"MoveToPoint","points":[[52.23125076293945,31.82121568629373]]},{"type":"AddLine","points":[[52.23125076293945,44.5625]]},{"type":"AddLine","points":[[91.15625,25.8253173828125]]},{"type":"AddLine","points":[[52.23125076293945,7.088134765625]]},{"type":"AddLine","points":[[52.23125076293945,19.82941907933127]]},{"type":"AddLine","points":[[5.627685546875,19.82941907933127]]},{"type":"AddLine","points":[[5.627685546875,31.82121568629373]]},{"type":"CloseSubpath"},{"type":"MoveToPoint","points":[[52.23125076293945,31.82121568629373]]}],"windingRule":0,"lineJoinStyle":0,"miterLimit":10},"isBackgroundTexture":true,"textBaseline":0,"isVerticalText":false,"textureType":5},"initialState":{"affineTransform":[1,0,0,1,0,0],"masksToBounds":false,"rotation":0,"scale":1,"position":{"pointX":42.872314453125,"pointY":18.911865234375},"width":97,"sublayerTransform":[1,0,0,0,0,1,0,0,0,0,1,0,0,0,0,1],"contentsRect":{"y":0,"x":0,"width":1,"height":1},"opacity":1,"edgeAntialiasingMask":0,"height":52,"hidden":true,"anchorPoint":{"pointX":0.5,"pointY":0.5}},"texture":"F103F82652D757B9580E25359DE65B05"}]}]},{"animations":[],"initialState":{"affineTransform":[1,0,0,1,0,0],"masksToBounds":false,"rotation":0,"scale":1,"position":{"pointX":960,"pointY":540},"width":1920,"sublayerTransform":[1,0,0,0,0,1,0,0,0,0,1,0,0,0,0,1],"contentsRect":{"y":0,"x":0,"width":1,"height":1},"opacity":1,"edgeAntialiasingMask":251658240,"height":1080,"hidden":false,"anchorPoint":{"pointX":0.5,"pointY":0.5}},"layers":[{"animations":[],"initialState":{"affineTransform":[1,0,0,1,0,0],"masksToBounds":false,"rotation":0,"scale":1,"position":{"pointX":1417.860717773438,"pointY":498.7628173828125},"width":85.528564453125,"sublayerTransform":[1,0,0,0,0,1,0,0,0,0,1,0,0,0,0,1],"contentsRect":{"y":0,"x":0,"width":1,"height":1},"opacity":1,"edgeAntialiasingMask":251658240,"height":37.474365234375,"hidden":false,"anchorPoint":{"pointX":0.5,"pointY":0.5}},"objectID":"F89DFC79-0A12-4877-8319-F35C27C35ACC","layers":[{"animations":[],"layers":[],"texturedRectangle":{"singleTextureOpacity":1,"textXHeight":0,"shapePath":{"lineWidth":1,"flatness":0.6,"lineCapStyle":0,"elements":[{"type":"MoveToPoint","points":[[51.70000076293945,31.75871568629373]]},{"type":"AddLine","points":[[51.70000076293945,44.5]]},{"type":"AddLine","points":[[90.625,25.7628173828125]]},{"type":"AddLine","points":[[51.70000076293945,7.025634765625]]},{"type":"AddLine","points":[[51.70000076293945,19.76691907933127]]},{"type":"AddLine","points":[[5.096435546875,19.76691907933127]]},{"type":"AddLine","points":[[5.096435546875,31.75871568629373]]},{"type":"CloseSubpath"},{"type":"MoveToPoint","points":[[51.70000076293945,31.75871568629373]]}],"windingRule":0,"lineJoinStyle":0,"miterLimit":10},"isBackgroundTexture":true,"textBaseline":0,"isVerticalText":false,"textureType":5},"initialState":{"affineTransform":[1,0,0,1,0,0],"masksToBounds":false,"rotation":0,"scale":1,"position":{"pointX":42.903564453125,"pointY":18.974365234375},"width":96,"sublayerTransform":[1,0,0,0,0,1,0,0,0,0,1,0,0,0,0,1],"contentsRect":{"y":0,"x":0,"width":1,"height":1},"opacity":1,"edgeAntialiasingMask":0,"height":52,"hidden":true,"anchorPoint":{"pointX":0.5,"pointY":0.5}},"texture":"A39890CA799CAA1EBF0B9EE97BE370DD"}]}]},{"animations":[],"initialState":{"affineTransform":[1,0,0,1,0,0],"masksToBounds":false,"rotation":0,"scale":1,"position":{"pointX":960,"pointY":540},"width":1920,"sublayerTransform":[1,0,0,0,0,1,0,0,0,0,1,0,0,0,0,1],"contentsRect":{"y":0,"x":0,"width":1,"height":1},"opacity":1,"edgeAntialiasingMask":251658240,"height":1080,"hidden":false,"anchorPoint":{"pointX":0.5,"pointY":0.5}},"layers":[{"animations":[],"initialState":{"affineTransform":[1,0,0,1,0,0],"masksToBounds":false,"rotation":0,"scale":1,"position":{"pointX":878.8294677734375,"pointY":679.7315673828125},"width":85.528564453125,"sublayerTransform":[1,0,0,0,0,1,0,0,0,0,1,0,0,0,0,1],"contentsRect":{"y":0,"x":0,"width":1,"height":1},"opacity":1,"edgeAntialiasingMask":251658240,"height":37.474365234375,"hidden":false,"anchorPoint":{"pointX":0.5,"pointY":0.5}},"objectID":"77840946-1951-4B22-A97E-947F818B7BEB","layers":[{"animations":[],"layers":[],"texturedRectangle":{"singleTextureOpacity":1,"textXHeight":0,"shapePath":{"lineWidth":1,"flatness":0.6,"lineCapStyle":0,"elements":[{"type":"MoveToPoint","points":[[51.66875076293945,32.72746568629373]]},{"type":"AddLine","points":[[51.66875076293945,45.46875]]},{"type":"AddLine","points":[[90.59375,26.7315673828125]]},{"type":"AddLine","points":[[51.66875076293945,7.994384765625]]},{"type":"AddLine","points":[[51.66875076293945,20.73566907933127]]},{"type":"AddLine","points":[[5.065185546875,20.73566907933127]]},{"type":"AddLine","points":[[5.065185546875,32.72746568629373]]},{"type":"CloseSubpath"},{"type":"MoveToPoint","points":[[51.66875076293945,32.72746568629373]]}],"windingRule":0,"lineJoinStyle":0,"miterLimit":10},"isBackgroundTexture":true,"textBaseline":0,"isVerticalText":false,"textureType":5},"initialState":{"affineTransform":[1,0,0,1,0,0],"masksToBounds":false,"rotation":0,"scale":1,"position":{"pointX":42.934814453125,"pointY":18.505615234375},"width":96,"sublayerTransform":[1,0,0,0,0,1,0,0,0,0,1,0,0,0,0,1],"contentsRect":{"y":0,"x":0,"width":1,"height":1},"opacity":1,"edgeAntialiasingMask":0,"height":53,"hidden":true,"anchorPoint":{"pointX":0.5,"pointY":0.5}},"texture":"0DB6C110A922BC749D0CD1B6CECD6B2C"}]}]},{"animations":[],"initialState":{"affineTransform":[1,0,0,1,0,0],"masksToBounds":false,"rotation":0,"scale":1,"position":{"pointX":960,"pointY":540},"width":1920,"sublayerTransform":[1,0,0,0,0,1,0,0,0,0,1,0,0,0,0,1],"contentsRect":{"y":0,"x":0,"width":1,"height":1},"opacity":1,"edgeAntialiasingMask":251658240,"height":1080,"hidden":false,"anchorPoint":{"pointX":0.5,"pointY":0.5}},"layers":[{"animations":[],"initialState":{"affineTransform":[1,0,0,1,0,0],"masksToBounds":false,"rotation":0,"scale":1,"position":{"pointX":53.18893432617188,"pointY":53.18893432617188},"width":106.3778686523438,"sublayerTransform":[1,0,0,0,0,1,0,0,0,0,1,0,0,0,0,1],"contentsRect":{"y":0,"x":0,"width":1,"height":1},"opacity":1,"edgeAntialiasingMask":251658240,"height":106.3778686523438,"hidden":false,"anchorPoint":{"pointX":0.5,"pointY":0.5}},"objectID":"9DF650DA-85FF-4A89-9439-7131CE974892","layers":[{"animations":[],"layers":[],"texturedRectangle":{"isBackgroundTexture":true,"singleTextureOpacity":1,"textureType":5,"textBaseline":0,"textXHeight":0,"isVerticalText":false},"initialState":{"affineTransform":[1,0,0,1,0,0],"masksToBounds":false,"rotation":0,"scale":1,"position":{"pointX":53.5,"pointY":53.5},"width":109,"sublayerTransform":[1,0,0,0,0,1,0,0,0,0,1,0,0,0,0,1],"contentsRect":{"y":0,"x":0,"width":1,"height":1},"opacity":1,"edgeAntialiasingMask":0,"height":109,"hidden":false,"anchorPoint":{"pointX":0.5,"pointY":0.5}},"texture":"0AFD695DF00B56CFBA35BE358E1C9D6B"}]}]},{"animations":[],"initialState":{"affineTransform":[1,0,0,1,0,0],"masksToBounds":false,"rotation":0,"scale":1,"position":{"pointX":960,"pointY":540},"width":1920,"sublayerTransform":[1,0,0,0,0,1,0,0,0,0,1,0,0,0,0,1],"contentsRect":{"y":0,"x":0,"width":1,"height":1},"opacity":1,"edgeAntialiasingMask":251658240,"height":1080,"hidden":false,"anchorPoint":{"pointX":0.5,"pointY":0.5}},"layers":[{"animations":[],"initialState":{"affineTransform":[1,0,0,1,0,0],"masksToBounds":false,"rotation":0,"scale":1,"position":{"pointX":84.97068786621094,"pointY":1029.642951965332},"width":150.0625,"sublayerTransform":[1,0,0,0,0,1,0,0,0,0,1,0,0,0,0,1],"contentsRect":{"y":0,"x":0,"width":1,"height":1},"opacity":1,"edgeAntialiasingMask":251658240,"height":78.66712951660156,"hidden":false,"anchorPoint":{"pointX":0.5,"pointY":0.5}},"objectID":"69A5A788-181A-477C-9D91-04F6D73E817D","layers":[{"animations":[],"layers":[],"texturedRectangle":{"isBackgroundTexture":true,"singleTextureOpacity":1,"textureType":5,"textBaseline":0,"textXHeight":0,"isVerticalText":false},"initialState":{"affineTransform":[1,0,0,1,0,0],"masksToBounds":false,"rotation":0,"scale":1,"position":{"pointX":75.06056213378906,"pointY":39.19061279296875},"width":154,"sublayerTransform":[1,0,0,0,0,1,0,0,0,0,1,0,0,0,0,1],"contentsRect":{"y":0,"x":0,"width":1,"height":1},"opacity":1,"edgeAntialiasingMask":0,"height":81,"hidden":false,"anchorPoint":{"pointX":0.5,"pointY":0.5}},"texture":"0A76BA58503224FEEDCA4872F8618A58"}]}]},{"animations":[],"initialState":{"affineTransform":[1,0,0,1,0,0],"masksToBounds":false,"rotation":0,"scale":1,"position":{"pointX":960,"pointY":540},"width":1920,"sublayerTransform":[1,0,0,0,0,1,0,0,0,0,1,0,0,0,0,1],"contentsRect":{"y":0,"x":0,"width":1,"height":1},"opacity":1,"edgeAntialiasingMask":251658240,"height":1080,"hidden":false,"anchorPoint":{"pointX":0.5,"pointY":0.5}},"layers":[{"animations":[],"initialState":{"affineTransform":[1,0,0,1,0,0],"masksToBounds":false,"rotation":0,"scale":1,"position":{"pointX":1823.240089416504,"pointY":1029.475103378296},"width":149.7072296142578,"sublayerTransform":[1,0,0,0,0,1,0,0,0,0,1,0,0,0,0,1],"contentsRect":{"y":0,"x":0,"width":1,"height":1},"opacity":1,"edgeAntialiasingMask":251658240,"height":61.6969108581543,"hidden":false,"anchorPoint":{"pointX":0.5,"pointY":0.5}},"objectID":"03823446-722D-4302-AB95-2B53C52CF60E","layers":[{"animations":[],"layers":[],"texturedRectangle":{"isBackgroundTexture":true,"singleTextureOpacity":1,"textureType":5,"textBaseline":0,"textXHeight":0,"isVerticalText":false},"initialState":{"affineTransform":[1,0,0,1,0,0],"masksToBounds":false,"rotation":0,"scale":1,"position":{"pointX":75.113525390625,"pointY":30.87335205078125},"width":153,"sublayerTransform":[1,0,0,0,0,1,0,0,0,0,1,0,0,0,0,1],"contentsRect":{"y":0,"x":0,"width":1,"height":1},"opacity":1,"edgeAntialiasingMask":0,"height":65,"hidden":false,"anchorPoint":{"pointX":0.5,"pointY":0.5}},"texture":"F1E4F471EFBCA02A7A50F8183033FDEE"}]}]},{"animations":[],"initialState":{"affineTransform":[1,0,0,1,0,0],"masksToBounds":false,"rotation":0,"scale":1,"position":{"pointX":960,"pointY":540},"width":1920,"sublayerTransform":[1,0,0,0,0,1,0,0,0,0,1,0,0,0,0,1],"contentsRect":{"y":0,"x":0,"width":1,"height":1},"opacity":1,"edgeAntialiasingMask":251658240,"height":1080,"hidden":false,"anchorPoint":{"pointX":0.5,"pointY":0.5}},"layers":[{"animations":[],"initialState":{"affineTransform":[1,0,0,1,0,0],"masksToBounds":false,"rotation":0,"scale":1,"position":{"pointX":1809.381950378418,"pointY":53.18893432617188},"width":166.3303070068359,"sublayerTransform":[1,0,0,0,0,1,0,0,0,0,1,0,0,0,0,1],"contentsRect":{"y":0,"x":0,"width":1,"height":1},"opacity":1,"edgeAntialiasingMask":251658240,"height":77.56935119628906,"hidden":false,"anchorPoint":{"pointX":0.5,"pointY":0.5}},"objectID":"F0CB2D3B-746D-4175-BEA3-CF2AAE4A4ACD","layers":[{"animations":[],"layers":[],"texturedRectangle":{"isBackgroundTexture":true,"singleTextureOpacity":1,"textureType":5,"textBaseline":0,"textXHeight":0,"isVerticalText":false},"initialState":{"affineTransform":[1,0,0,1,0,0],"masksToBounds":false,"rotation":0,"scale":1,"position":{"pointX":83.283203125,"pointY":38.59574127197266},"width":169,"sublayerTransform":[1,0,0,0,0,1,0,0,0,0,1,0,0,0,0,1],"contentsRect":{"y":0,"x":0,"width":1,"height":1},"opacity":1,"edgeAntialiasingMask":0,"height":80,"hidden":false,"anchorPoint":{"pointX":0.5,"pointY":0.5}},"texture":"3A6AA7E13049CA43A0D406F83530A09D"}]}]}]}},{"effects":[{"beginTime":0,"baseLayer":{"animations":[],"initialState":{"affineTransform":[1,0,0,1,0,0],"masksToBounds":false,"rotation":0,"scale":1,"position":{"pointX":960,"pointY":540},"width":1920,"sublayerTransform":[1,0,0,0,0,1,0,0,0,0,1,0,0,0,0,1],"contentsRect":{"y":0,"x":0,"width":1,"height":1},"opacity":1,"edgeAntialiasingMask":251658240,"height":1080,"hidden":false,"anchorPoint":{"pointX":0.5,"pointY":0.5}},"objectID":"0","layers":[{"animations":[],"initialState":{"affineTransform":[1,0,0,1,0,0],"masksToBounds":false,"rotation":0,"scale":1,"position":{"pointX":960,"pointY":540},"width":1920,"sublayerTransform":[1,0,0,0,0,1,0,0,0,0,1,-0.0003500791246677598,0,0,0,1],"contentsRect":{"y":0,"x":0,"width":1,"height":1},"opacity":1,"edgeAntialiasingMask":251658240,"height":1080,"hidden":false,"anchorPoint":{"pointX":0.5,"pointY":0.5}},"layers":[{"animations":[],"layers":[],"texturedRectangle":{"isBackgroundTexture":false,"singleTextureOpacity":1,"textureType":0,"textBaseline":0,"textXHeight":0,"isVerticalText":false},"initialState":{"affineTransform":[1,0,0,1,0,0],"masksToBounds":false,"rotation":0,"scale":1,"position":{"pointX":960,"pointY":540},"width":1920,"sublayerTransform":[1,0,0,0,0,1,0,0,0,0,1,0,0,0,0,1],"contentsRect":{"y":0,"x":0,"width":1,"height":1},"opacity":1,"edgeAntialiasingMask":0,"height":1080,"hidden":false,"anchorPoint":{"pointX":0.5,"pointY":0.5}},"texture":"32421F0B3E0C6634C0C341CD41DF516D"},{"animations":[{"timeOffset":0,"from":{"scalar":false},"beginTime":0,"repeatCount":0,"fillMode":"both","property":"hidden","autoreverses":false,"duration":0.01,"to":{"scalar":true}}],"layers":[],"texturedRectangle":{"isBackgroundTexture":false,"singleTextureOpacity":1,"textureType":0,"textBaseline":0,"textXHeight":0,"isVerticalText":false},"initialState":{"affineTransform":[1,0,0,1,0,0],"masksToBounds":false,"rotation":0,"scale":1,"position":{"pointX":960,"pointY":540},"width":1920,"sublayerTransform":[1,0,0,0,0,1,0,0,0,0,1,0,0,0,0,1],"contentsRect":{"y":0,"x":0,"width":1,"height":1},"opacity":1,"edgeAntialiasingMask":0,"height":1080,"hidden":false,"anchorPoint":{"pointX":0.5,"pointY":0.5}},"texture":"FB604898F4125EE5D77E90AA5878BA5A"}]}]},"effects":[],"duration":0.01,"type":"transition","name":"none","objectID":"0"}],"automaticPlay":false,"hyperlinks":[],"accessibility":[{"text":"No speed trap cameras","targetRectangle":{"y":785.7102661132812,"x":353.4913177490234,"width":352.15625,"height":38}},{"text":"blue dots","targetRectangle":{"y":861.7102661132812,"x":462.8814427490234,"width":133.376,"height":38}},{"text":"droppedImage.pdf","targetRectangle":{"y":0,"x":0,"width":106.3778686523438,"height":106.3778686523438}},{"text":"logo_idb_black.png","targetRectangle":{"y":14.40425872802734,"x":1726.216796875,"width":166.3303070068359,"height":77.56935119628906}},{"text":"Logo Waze Branco.png","targetRectangle":{"y":998.6266479492188,"x":1748.386474609375,"width":149.7072296142578,"height":61.6969108581543}},{"text":"AV. BRASIL / PRESIDENTE DUTRA","targetRectangle":{"y":18.81250262260437,"x":533.1060375509261,"width":853.7880000000004,"height":62.49163818359375}},{"text":"logo_vertical.png","targetRectangle":{"y":990.3093872070312,"x":9.939437866210938,"width":150.0625,"height":78.66712951660156}},{"text":"01-Brasil-Dutra.png","targetRectangle":{"y":1.84375,"x":1,"width":1918,"height":1183.539306640625}}],"baseLayer":{"animations":[],"initialState":{"affineTransform":[1,0,0,1,0,0],"masksToBounds":false,"rotation":0,"scale":1,"position":{"pointX":960,"pointY":540},"width":1920,"sublayerTransform":[1,0,0,0,0,1,0,0,0,0,1,0,0,0,0,1],"contentsRect":{"y":0,"x":0,"width":1,"height":1},"opacity":1,"edgeAntialiasingMask":251658240,"height":1080,"hidden":false,"anchorPoint":{"pointX":0.5,"pointY":0.5}},"objectID":"0","layers":[{"animations":[],"initialState":{"affineTransform":[1,0,0,1,0,0],"masksToBounds":false,"rotation":0,"scale":1,"position":{"pointX":960,"pointY":540},"width":1920,"sublayerTransform":[1,0,0,0,0,1,0,0,0,0,1,-0.0003500791246677598,0,0,0,1],"contentsRect":{"y":0,"x":0,"width":1,"height":1},"opacity":1,"edgeAntialiasingMask":251658240,"height":1080,"hidden":false,"anchorPoint":{"pointX":0.5,"pointY":0.5}},"layers":[{"animations":[],"layers":[],"texturedRectangle":{"isBackgroundTexture":false,"singleTextureOpacity":1,"textureType":0,"textBaseline":0,"textXHeight":0,"isVerticalText":false},"initialState":{"affineTransform":[1,0,0,1,0,0],"masksToBounds":false,"rotation":0,"scale":1,"position":{"pointX":960,"pointY":540},"width":1920,"sublayerTransform":[1,0,0,0,0,1,0,0,0,0,1,0,0,0,0,1],"contentsRect":{"y":0,"x":0,"width":1,"height":1},"opacity":1,"edgeAntialiasingMask":0,"height":1080,"hidden":false,"anchorPoint":{"pointX":0.5,"pointY":0.5}},"texture":"FB604898F4125EE5D77E90AA5878BA5A"}]}]}}]}